[{"_meta": {"retrieved_2nd_on": 1705953101}, "all_awardings": [], "approved_at_utc": null, "approved_by": null, "archived": false, "associated_award": null, "author": "[deleted]", "author_flair_background_color": "", "author_flair_css_class": null, "author_flair_template_id": null, "author_flair_text": null, "author_flair_text_color": "dark", "author_is_blocked": false, "awarders": [], "banned_at_utc": null, "banned_by": null, "body": "[deleted]", "can_gild": false, "can_mod_post": false, "collapsed": true, "collapsed_because_crowd_control": null, "collapsed_reason": null, "collapsed_reason_code": "DELETED", "comment_type": null, "controversiality": 0, "created": 1705823494, "created_utc": 1705823494, "distinguished": null, "downs": 0, "edited": false, "gilded": 0, "gildings": {}, "id": "kiv2l29", "is_submitter": false, "likes": null, "link_id": "t3_19b9stc", "locked": false, "mod_note": null, "mod_reason_by": null, "mod_reason_title": null, "mod_reports": [], "name": "t1_kiv2l29", "no_follow": true, "num_reports": 0, "parent_id": "t1_kiuxubk", "permalink": "/r/Indian_Academia/comments/19b9stc/how_is_christ_university_bengaluru_for_mca/kiv2l29/", "removal_reason": null, "replies": "", "report_reasons": [], "retrieved_on": 1705823511, "saved": false, "score": 1, "score_hidden": false, "send_replies": true, "stickied": false, "subreddit": "Indian_Academia", "subreddit_id": "t5_idfco", "subreddit_name_prefixed": "r/Indian_Academia", "subreddit_type": "public", "top_awarded_type": null, "total_awards_received": 0, "treatment_tags": [], "unrepliable_reason": null, "ups": 1, "user_reports": []}, {"_meta": {"retrieved_2nd_on": 1705949930}, "all_awardings": [], "approved_at_utc": null, "approved_by": null, "archived": false, "associated_award": null, "author": "materrwelonn", "author_flair_background_color": null, "author_flair_css_class": null, "author_flair_richtext": [], "author_flair_template_id": null, "author_flair_text": null, "author_flair_text_color": null, "author_flair_type": "text", "author_fullname": "t2_8kzg4sgtm", "author_is_blocked": false, "author_patreon_flair": false, "author_premium": false, "awarders": [], "banned_at_utc": null, "banned_by": null, "body": "What are your views on government institutions?", "can_gild": false, "can_mod_post": false, "collapsed": false, "collapsed_because_crowd_control": null, "collapsed_reason": null, "collapsed_reason_code": null, "comment_type": null, "controversiality": 0, "created": 1705820322, "created_utc": 1705820322, "distinguished": null, "downs": 0, "edited": false, "gilded": 0, "gildings": {}, "id": "kiuxubk", "is_submitter": false, "likes": null, "link_id": "t3_19b9stc", "locked": false, "mod_note": null, "mod_reason_by": null, "mod_reason_title": null, "mod_reports": [], "name": "t1_kiuxubk", "no_follow": true, "num_reports": 0, "parent_id": "t3_19b9stc", "permalink": "/r/Indian_Academia/comments/19b9stc/how_is_christ_university_bengaluru_for_mca/kiuxubk/", "removal_reason": null, "replies": "", "report_reasons": [], "retrieved_on": 1705820338, "saved": false, "score": 1, "score_hidden": false, "send_replies": true, "stickied": false, "subreddit": "Indian_Academia", "subreddit_id": "t5_idfco", "subreddit_name_prefixed": "r/Indian_Academia", "subreddit_type": "public", "top_awarded_type": null, "total_awards_received": 0, "treatment_tags": [], "unrepliable_reason": null, "ups": 1, "user_reports": []}, {"_meta": {"retrieved_2nd_on": 1705906956}, "all_awardings": [], "approved_at_utc": null, "approved_by": null, "archived": false, "associated_award": null, "author": "vxishnxv", "author_flair_background_color": null, "author_flair_css_class": null, "author_flair_richtext": [], "author_flair_template_id": null, "author_flair_text": null, "author_flair_text_color": null, "author_flair_type": "text", "author_fullname": "t2_46hd6yph", "author_is_blocked": false, "author_patreon_flair": false, "author_premium": false, "awarders": [], "banned_at_utc": null, "banned_by": null, "body": "VIT", "can_gild": false, "can_mod_post": false, "collapsed": false, "collapsed_because_crowd_control": null, "collapsed_reason": null, "collapsed_reason_code": null, "comment_type": null, "controversiality": 0, "created": 1705777348, "created_utc": 1705777348, "distinguished": null, "downs": 0, "edited": false, "gilded": 0, "gildings": {}, "id": "kiryt6y", "is_submitter": false, "likes": null, "link_id": "t3_19b9stc", "locked": false, "mod_note": null, "mod_reason_by": null, "mod_reason_title": null, "mod_reports": [], "name": "t1_kiryt6y", "no_follow": true, "num_reports": 0, "parent_id": "t3_19b9stc", "permalink": "/r/Indian_Academia/comments/19b9stc/how_is_christ_university_bengaluru_for_mca/kiryt6y/", "removal_reason": null, "replies": "", "report_reasons": [], "retrieved_on": 1705777364, "saved": false, "score": 1, "score_hidden": false, "send_replies": true, "stickied": false, "subreddit": "Indian_Academia", "subreddit_id": "t5_idfco", "subreddit_name_prefixed": "r/Indian_Academia", "subreddit_type": "public", "top_awarded_type": null, "total_awards_received": 0, "treatment_tags": [], "unrepliable_reason": null, "ups": 1, "user_reports": []}, {"_meta": {"retrieved_2nd_on": 1705879787}, "all_awardings": [], "approved_at_utc": null, "approved_by": null, "archived": false, "associated_award": null, "author": "AutoModerator", "author_flair_background_color": null, "author_flair_css_class": null, "author_flair_richtext": [], "author_flair_template_id": null, "author_flair_text": null, "author_flair_text_color": null, "author_flair_type": "text", "author_fullname": "t2_6l4z3", "author_is_blocked": false, "author_patreon_flair": false, "author_premium": true, "awarders": [], "banned_at_utc": null, "banned_by": null, "body": "Please remake your post in r/EngineeringAdmissions.\n\nIf your post is not related to engineering admissions, **please wait while the mods review your post**\n\nFor any further assistance, send us a Modmail.\n\nHere's a backup of your post:    \n\nTitle: How is Christ University Bengaluru for MCA compared to VIT Vellore MCA?  \nBody:  \n\nSo planning to join either of these?\nWhich would you recommend?\n\nmyquals: BSc(IT)\n\n*I am a bot, and this action was performed automatically. Please [contact the moderators of this subreddit](/message/compose/?to=/r/Indian_Academia) if you have any questions or concerns.*", "can_gild": false, "can_mod_post": false, "collapsed": false, "collapsed_because_crowd_control": null, "collapsed_reason": null, "collapsed_reason_code": null, "comment_type": null, "controversiality": 0, "created": 1705750181, "created_utc": 1705750181, "distinguished": "moderator", "downs": 0, "edited": false, "gilded": 0, "gildings": {}, "id": "kiq5nou", "is_submitter": false, "likes": null, "link_id": "t3_19b9stc", "locked": false, "mod_note": null, "mod_reason_by": null, "mod_reason_title": null, "mod_reports": [], "name": "t1_kiq5nou", "no_follow": true, "num_reports": 0, "parent_id": "t3_19b9stc", "permalink": "/r/Indian_Academia/comments/19b9stc/how_is_christ_university_bengaluru_for_mca/kiq5nou/", "removal_reason": null, "replies": "", "report_reasons": [], "retrieved_on": 1705750205, "saved": false, "score": 1, "score_hidden": false, "send_replies": false, "stickied": false, "subreddit": "Indian_Academia", "subreddit_id": "t5_idfco", "subreddit_name_prefixed": "r/Indian_Academia", "subreddit_type": "public", "top_awarded_type": null, "total_awards_received": 0, "treatment_tags": [], "unrepliable_reason": null, "ups": 1, "user_reports": []}]