[{"_meta": {"retrieved_2nd_on": 1717373760}, "all_awardings": [], "approved_at_utc": null, "approved_by": null, "archived": false, "associated_award": null, "author": "Emergency_Pipe1574", "author_flair_background_color": null, "author_flair_css_class": null, "author_flair_richtext": [], "author_flair_template_id": null, "author_flair_text": null, "author_flair_text_color": null, "author_flair_type": "text", "author_fullname": "t2_99vddo9c", "author_is_blocked": false, "author_patreon_flair": false, "author_premium": false, "awarders": [], "banned_at_utc": null, "banned_by": null, "body": "Alright thanks a lot for the Guidance", "can_gild": false, "can_mod_post": false, "collapsed": false, "collapsed_because_crowd_control": null, "collapsed_reason": null, "collapsed_reason_code": null, "comment_type": null, "controversiality": 0, "created": 1717244152, "created_utc": 1717244152, "distinguished": null, "downs": 0, "edited": false, "gilded": 0, "gildings": {}, "id": "l6m5k2z", "is_submitter": true, "likes": null, "link_id": "t3_1d5hmlh", "locked": false, "mod_note": null, "mod_reason_by": null, "mod_reason_title": null, "mod_reports": [], "name": "t1_l6m5k2z", "no_follow": true, "num_reports": null, "parent_id": "t1_l6lptml", "permalink": "/r/Vit/comments/1d5hmlh/vit_chennai_eee_branch_need_guidance/l6m5k2z/", "removal_reason": null, "replies": "", "report_reasons": null, "retrieved_on": 1717244166, "saved": false, "score": 2, "score_hidden": false, "send_replies": true, "stickied": false, "subreddit": "Vit", "subreddit_id": "t5_2qvwr", "subreddit_name_prefixed": "r/Vit", "subreddit_type": "public", "top_awarded_type": null, "total_awards_received": 0, "treatment_tags": [], "unrepliable_reason": null, "ups": 2, "user_reports": []}, {"_meta": {"retrieved_2nd_on": 1717367865}, "all_awardings": [], "approved_at_utc": null, "approved_by": null, "archived": false, "associated_award": null, "author": "ParsleyOld349", "author_flair_background_color": null, "author_flair_css_class": null, "author_flair_richtext": [], "author_flair_template_id": null, "author_flair_text": null, "author_flair_text_color": null, "author_flair_type": "text", "author_fullname": "t2_111chva0jx", "author_is_blocked": false, "author_patreon_flair": false, "author_premium": false, "awarders": [], "banned_at_utc": null, "banned_by": null, "body": "45k", "can_gild": false, "can_mod_post": false, "collapsed": false, "collapsed_because_crowd_control": null, "collapsed_reason": null, "collapsed_reason_code": null, "comment_type": null, "controversiality": 0, "created": 1717238259, "created_utc": 1717238259, "distinguished": null, "downs": 0, "edited": false, "gilded": 0, "gildings": {}, "id": "l6lug2r", "is_submitter": false, "likes": null, "link_id": "t3_1d5hmlh", "locked": false, "mod_note": null, "mod_reason_by": null, "mod_reason_title": null, "mod_reports": [], "name": "t1_l6lug2r", "no_follow": true, "num_reports": null, "parent_id": "t1_l6lpkrj", "permalink": "/r/Vit/comments/1d5hmlh/vit_chennai_eee_branch_need_guidance/l6lug2r/", "removal_reason": null, "replies": "", "report_reasons": null, "retrieved_on": 1717238282, "saved": false, "score": 1, "score_hidden": false, "send_replies": true, "stickied": false, "subreddit": "Vit", "subreddit_id": "t5_2qvwr", "subreddit_name_prefixed": "r/Vit", "subreddit_type": "public", "top_awarded_type": null, "total_awards_received": 0, "treatment_tags": [], "unrepliable_reason": null, "ups": 1, "user_reports": []}, {"_meta": {"retrieved_2nd_on": 1717364936}, "all_awardings": [], "approved_at_utc": null, "approved_by": null, "archived": false, "associated_award": null, "author": "Decent-Coach-3384", "author_flair_background_color": null, "author_flair_css_class": null, "author_flair_richtext": [], "author_flair_template_id": null, "author_flair_text": null, "author_flair_text_color": null, "author_flair_type": "text", "author_fullname": "t2_wczzo05kw", "author_is_blocked": false, "author_patreon_flair": false, "author_premium": false, "awarders": [], "banned_at_utc": null, "banned_by": null, "body": "Take LNCT bhopal CSE ,\n\n first of all avg of lnct ( 8lpa ) is better than eee vit c (6 lpa)\n\nSecondly you would able to save lot of money which can be later utlised for MTech/MBA/MS\n\nThirdly EEE is a very hectic branch and LNCT cse would be better as she would be having time to work on coding skills and get good cgpa.\n\nSo with all this in mind , if u have oppurtunity for LNCT CSE go for it sure , its much better", "can_gild": false, "can_mod_post": false, "collapsed": false, "collapsed_because_crowd_control": null, "collapsed_reason": null, "collapsed_reason_code": null, "comment_type": null, "controversiality": 0, "created": 1717235327, "created_utc": 1717235327, "distinguished": null, "downs": 0, "edited": false, "gilded": 0, "gildings": {}, "id": "l6lptml", "is_submitter": false, "likes": null, "link_id": "t3_1d5hmlh", "locked": false, "mod_note": null, "mod_reason_by": null, "mod_reason_title": null, "mod_reports": [], "name": "t1_l6lptml", "no_follow": true, "num_reports": null, "parent_id": "t3_1d5hmlh", "permalink": "/r/Vit/comments/1d5hmlh/vit_chennai_eee_branch_need_guidance/l6lptml/", "removal_reason": null, "replies": "", "report_reasons": null, "retrieved_on": 1717235341, "saved": false, "score": 1, "score_hidden": false, "send_replies": true, "stickied": false, "subreddit": "Vit", "subreddit_id": "t5_2qvwr", "subreddit_name_prefixed": "r/Vit", "subreddit_type": "public", "top_awarded_type": null, "total_awards_received": 0, "treatment_tags": [], "unrepliable_reason": null, "ups": 1, "user_reports": []}, {"_meta": {"retrieved_2nd_on": 1717364760}, "all_awardings": [], "approved_at_utc": null, "approved_by": null, "archived": false, "associated_award": null, "author": "Decent-Coach-3384", "author_flair_background_color": null, "author_flair_css_class": null, "author_flair_richtext": [], "author_flair_template_id": null, "author_flair_text": null, "author_flair_text_color": null, "author_flair_type": "text", "author_fullname": "t2_wczzo05kw", "author_is_blocked": false, "author_patreon_flair": false, "author_premium": false, "awarders": [], "banned_at_utc": null, "banned_by": null, "body": "Your rank bro ?", "can_gild": false, "can_mod_post": false, "collapsed": false, "collapsed_because_crowd_control": null, "collapsed_reason": null, "collapsed_reason_code": null, "comment_type": null, "controversiality": 0, "created": 1717235151, "created_utc": 1717235151, "distinguished": null, "downs": 0, "edited": false, "gilded": 0, "gildings": {}, "id": "l6lpkrj", "is_submitter": false, "likes": null, "link_id": "t3_1d5hmlh", "locked": false, "mod_note": null, "mod_reason_by": null, "mod_reason_title": null, "mod_reports": [], "name": "t1_l6lpkrj", "no_follow": true, "num_reports": null, "parent_id": "t1_l6leuap", "permalink": "/r/Vit/comments/1d5hmlh/vit_chennai_eee_branch_need_guidance/l6lpkrj/", "removal_reason": null, "replies": "", "report_reasons": null, "retrieved_on": 1717235165, "saved": false, "score": 1, "score_hidden": false, "send_replies": true, "stickied": false, "subreddit": "Vit", "subreddit_id": "t5_2qvwr", "subreddit_name_prefixed": "r/Vit", "subreddit_type": "public", "top_awarded_type": null, "total_awards_received": 0, "treatment_tags": [], "unrepliable_reason": null, "ups": 1, "user_reports": []}, {"_meta": {"retrieved_2nd_on": 1717359843}, "all_awardings": [], "approved_at_utc": null, "approved_by": null, "archived": false, "associated_award": null, "author": "maderchodbakchod", "author_flair_background_color": null, "author_flair_css_class": null, "author_flair_richtext": [], "author_flair_template_id": null, "author_flair_text": null, "author_flair_text_color": null, "author_flair_type": "text", "author_fullname": "t2_9tod51sml", "author_is_blocked": false, "author_patreon_flair": false, "author_premium": false, "awarders": [], "banned_at_utc": null, "banned_by": null, "body": "Same", "can_gild": false, "can_mod_post": false, "collapsed": false, "collapsed_because_crowd_control": null, "collapsed_reason": null, "collapsed_reason_code": null, "comment_type": null, "controversiality": 0, "created": 1717230237, "created_utc": 1717230237, "distinguished": null, "downs": 0, "edited": false, "gilded": 0, "gildings": {}, "id": "l6linef", "is_submitter": false, "likes": null, "link_id": "t3_1d5hmlh", "locked": false, "mod_note": null, "mod_reason_by": null, "mod_reason_title": null, "mod_reports": [], "name": "t1_l6linef", "no_follow": true, "num_reports": null, "parent_id": "t3_1d5hmlh", "permalink": "/r/Vit/comments/1d5hmlh/vit_chennai_eee_branch_need_guidance/l6linef/", "removal_reason": null, "replies": "", "report_reasons": null, "retrieved_on": 1717230255, "saved": false, "score": 2, "score_hidden": false, "send_replies": true, "stickied": false, "subreddit": "Vit", "subreddit_id": "t5_2qvwr", "subreddit_name_prefixed": "r/Vit", "subreddit_type": "public", "top_awarded_type": null, "total_awards_received": 0, "treatment_tags": [], "unrepliable_reason": null, "ups": 2, "user_reports": []}, {"_meta": {"retrieved_2nd_on": 1717358919}, "all_awardings": [], "approved_at_utc": null, "approved_by": null, "archived": false, "associated_award": null, "author": "Emergency_Pipe1574", "author_flair_background_color": null, "author_flair_css_class": null, "author_flair_richtext": [], "author_flair_template_id": null, "author_flair_text": null, "author_flair_text_color": null, "author_flair_type": "text", "author_fullname": "t2_99vddo9c", "author_is_blocked": false, "author_patreon_flair": false, "author_premium": false, "awarders": [], "banned_at_utc": null, "banned_by": null, "body": "Alright! Thanks for the Guidance", "can_gild": false, "can_mod_post": false, "collapsed": false, "collapsed_because_crowd_control": null, "collapsed_reason": null, "collapsed_reason_code": null, "comment_type": null, "controversiality": 0, "created": 1717229310, "created_utc": 1717229310, "distinguished": null, "downs": 0, "edited": false, "gilded": 0, "gildings": {}, "id": "l6lhb5x", "is_submitter": true, "likes": null, "link_id": "t3_1d5hmlh", "locked": false, "mod_note": null, "mod_reason_by": null, "mod_reason_title": null, "mod_reports": [], "name": "t1_l6lhb5x", "no_follow": true, "num_reports": null, "parent_id": "t1_l6lgu8z", "permalink": "/r/Vit/comments/1d5hmlh/vit_chennai_eee_branch_need_guidance/l6lhb5x/", "removal_reason": null, "replies": "", "report_reasons": null, "retrieved_on": 1717229324, "saved": false, "score": 1, "score_hidden": false, "send_replies": true, "stickied": false, "subreddit": "Vit", "subreddit_id": "t5_2qvwr", "subreddit_name_prefixed": "r/Vit", "subreddit_type": "public", "top_awarded_type": null, "total_awards_received": 0, "treatment_tags": [], "unrepliable_reason": null, "ups": 1, "user_reports": []}, {"_meta": {"retrieved_2nd_on": 1717358864}, "all_awardings": [], "approved_at_utc": null, "approved_by": null, "archived": false, "associated_award": null, "author": "[deleted]", "author_flair_background_color": "", "author_flair_css_class": null, "author_flair_template_id": null, "author_flair_text": null, "author_flair_text_color": "dark", "author_is_blocked": false, "awarders": [], "banned_at_utc": null, "banned_by": null, "body": "[deleted]", "can_gild": false, "can_mod_post": false, "collapsed": false, "collapsed_because_crowd_control": null, "collapsed_reason": null, "collapsed_reason_code": null, "comment_type": null, "controversiality": 0, "created": 1717229259, "created_utc": 1717229259, "distinguished": null, "downs": 0, "edited": false, "gilded": 0, "gildings": {}, "id": "l6lh8jn", "is_submitter": false, "likes": null, "link_id": "t3_1d5hmlh", "locked": false, "mod_note": null, "mod_reason_by": null, "mod_reason_title": null, "mod_reports": [], "name": "t1_l6lh8jn", "no_follow": true, "num_reports": null, "parent_id": "t3_1d5hmlh", "permalink": "/r/Vit/comments/1d5hmlh/vit_chennai_eee_branch_need_guidance/l6lh8jn/", "removal_reason": null, "replies": "", "report_reasons": null, "retrieved_on": 1717229282, "saved": false, "score": 1, "score_hidden": false, "send_replies": true, "stickied": false, "subreddit": "Vit", "subreddit_id": "t5_2qvwr", "subreddit_name_prefixed": "r/Vit", "subreddit_type": "public", "top_awarded_type": null, "total_awards_received": 0, "treatment_tags": [], "unrepliable_reason": null, "ups": 1, "user_reports": []}, {"_meta": {"is_edited": true, "retrieved_2nd_on": 1717358591}, "all_awardings": [], "approved_at_utc": null, "approved_by": null, "archived": false, "associated_award": null, "author": "ParsleyOld349", "author_flair_background_color": null, "author_flair_css_class": null, "author_flair_richtext": [], "author_flair_template_id": null, "author_flair_text": null, "author_flair_text_color": null, "author_flair_type": "text", "author_fullname": "t2_111chva0jx", "author_is_blocked": false, "author_patreon_flair": false, "author_premium": false, "awarders": [], "banned_at_utc": null, "banned_by": null, "body": "Not true tho, anyone can be a coder. It's up to you mate, if u want good college join vit or if u want the branch go for whichever one u wrote", "can_gild": false, "can_mod_post": false, "collapsed": false, "collapsed_because_crowd_control": null, "collapsed_reason": null, "collapsed_reason_code": null, "comment_type": null, "controversiality": 0, "created": 1717228983, "created_utc": 1717228983, "distinguished": null, "downs": 0, "edited": false, "gilded": 0, "gildings": {}, "id": "l6lgu8z", "is_submitter": false, "likes": null, "link_id": "t3_1d5hmlh", "locked": false, "mod_note": null, "mod_reason_by": null, "mod_reason_title": null, "mod_reports": [], "name": "t1_l6lgu8z", "no_follow": true, "num_reports": null, "parent_id": "t1_l6lf5st", "permalink": "/r/Vit/comments/1d5hmlh/vit_chennai_eee_branch_need_guidance/l6lgu8z/", "removal_reason": null, "replies": "", "report_reasons": null, "retrieved_on": 1717228997, "saved": false, "score": 1, "score_hidden": false, "send_replies": true, "stickied": false, "subreddit": "Vit", "subreddit_id": "t5_2qvwr", "subreddit_name_prefixed": "r/Vit", "subreddit_type": "public", "top_awarded_type": null, "total_awards_received": 0, "treatment_tags": [], "unrepliable_reason": null, "ups": 1, "user_reports": []}, {"_meta": {"is_edited": true, "retrieved_2nd_on": 1717357432}, "all_awardings": [], "approved_at_utc": null, "approved_by": null, "archived": false, "associated_award": null, "author": "Emergency_Pipe1574", "author_flair_background_color": null, "author_flair_css_class": null, "author_flair_richtext": [], "author_flair_template_id": null, "author_flair_text": null, "author_flair_text_color": null, "author_flair_type": "text", "author_fullname": "t2_99vddo9c", "author_is_blocked": false, "author_patreon_flair": false, "author_premium": false, "awarders": [], "banned_at_utc": null, "banned_by": null, "body": "Thank you for replying \n\nso the opportunities for the Core Branch is less if you are not a topper \n\nRight ?", "can_gild": false, "can_mod_post": false, "collapsed": false, "collapsed_because_crowd_control": null, "collapsed_reason": null, "collapsed_reason_code": null, "comment_type": null, "controversiality": 0, "created": 1717227826, "created_utc": 1717227826, "distinguished": null, "downs": 0, "edited": false, "gilded": 0, "gildings": {}, "id": "l6lf5st", "is_submitter": true, "likes": null, "link_id": "t3_1d5hmlh", "locked": false, "mod_note": null, "mod_reason_by": null, "mod_reason_title": null, "mod_reports": [], "name": "t1_l6lf5st", "no_follow": true, "num_reports": null, "parent_id": "t1_l6leuap", "permalink": "/r/Vit/comments/1d5hmlh/vit_chennai_eee_branch_need_guidance/l6lf5st/", "removal_reason": null, "replies": "", "report_reasons": null, "retrieved_on": 1717227841, "saved": false, "score": 1, "score_hidden": false, "send_replies": true, "stickied": false, "subreddit": "Vit", "subreddit_id": "t5_2qvwr", "subreddit_name_prefixed": "r/Vit", "subreddit_type": "public", "top_awarded_type": null, "total_awards_received": 0, "treatment_tags": [], "unrepliable_reason": null, "ups": 1, "user_reports": []}, {"_meta": {"retrieved_2nd_on": 1717357377}, "all_awardings": [], "approved_at_utc": null, "approved_by": null, "archived": false, "associated_award": null, "author": "Emergency_Pipe1574", "author_flair_background_color": null, "author_flair_css_class": null, "author_flair_richtext": [], "author_flair_template_id": null, "author_flair_text": null, "author_flair_text_color": null, "author_flair_type": "text", "author_fullname": "t2_99vddo9c", "author_is_blocked": false, "author_patreon_flair": false, "author_premium": false, "awarders": [], "banned_at_utc": null, "banned_by": null, "body": "45000 something", "can_gild": false, "can_mod_post": false, "collapsed": false, "collapsed_because_crowd_control": null, "collapsed_reason": null, "collapsed_reason_code": null, "comment_type": null, "controversiality": 0, "created": 1717227767, "created_utc": 1717227767, "distinguished": null, "downs": 0, "edited": false, "gilded": 0, "gildings": {}, "id": "l6lf2oz", "is_submitter": true, "likes": null, "link_id": "t3_1d5hmlh", "locked": false, "mod_note": null, "mod_reason_by": null, "mod_reason_title": null, "mod_reports": [], "name": "t1_l6lf2oz", "no_follow": true, "num_reports": null, "parent_id": "t1_l6lem34", "permalink": "/r/Vit/comments/1d5hmlh/vit_chennai_eee_branch_need_guidance/l6lf2oz/", "removal_reason": null, "replies": "", "report_reasons": null, "retrieved_on": 1717227794, "saved": false, "score": 1, "score_hidden": false, "send_replies": true, "stickied": false, "subreddit": "Vit", "subreddit_id": "t5_2qvwr", "subreddit_name_prefixed": "r/Vit", "subreddit_type": "public", "top_awarded_type": null, "total_awards_received": 0, "treatment_tags": [], "unrepliable_reason": null, "ups": 1, "user_reports": []}, {"_meta": {"retrieved_2nd_on": 1717357218}, "all_awardings": [], "approved_at_utc": null, "approved_by": null, "archived": false, "associated_award": null, "author": "ParsleyOld349", "author_flair_background_color": null, "author_flair_css_class": null, "author_flair_richtext": [], "author_flair_template_id": null, "author_flair_text": null, "author_flair_text_color": null, "author_flair_type": "text", "author_fullname": "t2_111chva0jx", "author_is_blocked": false, "author_patreon_flair": false, "author_premium": false, "awarders": [], "banned_at_utc": null, "banned_by": null, "body": "Hii, I'm alloted in same branch in the same cat. I got in touch with a cs proof there and she mentioned this below.\n1) the dept is ranked 7th nationally\n2)the faculties are highly experienced \n3) the field has seen in a increase in demands compared to last year's due to the introduction of ev vehicle tech and also need of the hour (renewable energy)\n4) placement wise, core companies do visit but only take the toppers. Avg package was 6lpa", "can_gild": false, "can_mod_post": false, "collapsed": false, "collapsed_because_crowd_control": null, "collapsed_reason": null, "collapsed_reason_code": null, "comment_type": null, "controversiality": 0, "created": 1717227609, "created_utc": 1717227609, "distinguished": null, "downs": 0, "edited": false, "gilded": 0, "gildings": {}, "id": "l6leuap", "is_submitter": false, "likes": null, "link_id": "t3_1d5hmlh", "locked": false, "mod_note": null, "mod_reason_by": null, "mod_reason_title": null, "mod_reports": [], "name": "t1_l6leuap", "no_follow": false, "num_reports": null, "parent_id": "t3_1d5hmlh", "permalink": "/r/Vit/comments/1d5hmlh/vit_chennai_eee_branch_need_guidance/l6leuap/", "removal_reason": null, "replies": "", "report_reasons": null, "retrieved_on": 1717227631, "saved": false, "score": 3, "score_hidden": false, "send_replies": true, "stickied": false, "subreddit": "Vit", "subreddit_id": "t5_2qvwr", "subreddit_name_prefixed": "r/Vit", "subreddit_type": "public", "top_awarded_type": null, "total_awards_received": 0, "treatment_tags": [], "unrepliable_reason": null, "ups": 3, "user_reports": []}, {"_meta": {"retrieved_2nd_on": 1717357059}, "all_awardings": [], "approved_at_utc": null, "approved_by": null, "archived": false, "associated_award": null, "author": "Decent-Coach-3384", "author_flair_background_color": null, "author_flair_css_class": null, "author_flair_richtext": [], "author_flair_template_id": null, "author_flair_text": null, "author_flair_text_color": null, "author_flair_type": "text", "author_fullname": "t2_wczzo05kw", "author_is_blocked": false, "author_patreon_flair": false, "author_premium": false, "awarders": [], "banned_at_utc": null, "banned_by": null, "body": "Her rank ?", "can_gild": false, "can_mod_post": false, "collapsed": false, "collapsed_because_crowd_control": null, "collapsed_reason": null, "collapsed_reason_code": null, "comment_type": null, "controversiality": 0, "created": 1717227454, "created_utc": 1717227454, "distinguished": null, "downs": 0, "edited": false, "gilded": 0, "gildings": {}, "id": "l6lem34", "is_submitter": false, "likes": null, "link_id": "t3_1d5hmlh", "locked": false, "mod_note": null, "mod_reason_by": null, "mod_reason_title": null, "mod_reports": [], "name": "t1_l6lem34", "no_follow": true, "num_reports": null, "parent_id": "t3_1d5hmlh", "permalink": "/r/Vit/comments/1d5hmlh/vit_chennai_eee_branch_need_guidance/l6lem34/", "removal_reason": null, "replies": "", "report_reasons": null, "retrieved_on": 1717227477, "saved": false, "score": 1, "score_hidden": false, "send_replies": true, "stickied": false, "subreddit": "Vit", "subreddit_id": "t5_2qvwr", "subreddit_name_prefixed": "r/Vit", "subreddit_type": "public", "top_awarded_type": null, "total_awards_received": 0, "treatment_tags": [], "unrepliable_reason": null, "ups": 1, "user_reports": []}]