[{"_meta": {"retrieved_2nd_on": 1722889585}, "all_awardings": [], "approved_at_utc": null, "approved_by": null, "archived": false, "associated_award": null, "author": "Outside-Tadpole-5288", "author_flair_background_color": null, "author_flair_css_class": null, "author_flair_richtext": [], "author_flair_template_id": null, "author_flair_text": null, "author_flair_text_color": null, "author_flair_type": "text", "author_fullname": "t2_yi5lp70p8", "author_is_blocked": false, "author_patreon_flair": false, "author_premium": false, "awarders": [], "banned_at_utc": null, "banned_by": null, "body": "My bad bro", "can_gild": false, "can_mod_post": false, "collapsed": false, "collapsed_because_crowd_control": null, "collapsed_reason": null, "collapsed_reason_code": null, "comment_type": null, "controversiality": 0, "created": 1722759976, "created_utc": 1722759976, "distinguished": null, "downs": 0, "edited": false, "gilded": 0, "gildings": {}, "id": "lgfbayi", "is_submitter": false, "likes": null, "link_id": "t3_1ehapj2", "locked": false, "mod_note": null, "mod_reason_by": null, "mod_reason_title": null, "mod_reports": [], "name": "t1_lgfbayi", "no_follow": true, "num_reports": null, "parent_id": "t1_lgf31i7", "permalink": "/r/Btechtards/comments/1ehapj2/tiering_of_colleges_does_not_make_any_sense/lgfbayi/", "removal_reason": null, "replies": "", "report_reasons": null, "retrieved_on": 1722759991, "saved": false, "score": 1, "score_hidden": false, "send_replies": true, "stickied": false, "subreddit": "Btechtards", "subreddit_id": "t5_56z50y", "subreddit_name_prefixed": "r/Btechtards", "subreddit_type": "public", "top_awarded_type": null, "total_awards_received": 0, "treatment_tags": [], "unrepliable_reason": null, "ups": 1, "user_reports": []}, {"_meta": {"retrieved_2nd_on": 1722884094}, "all_awardings": [], "approved_at_utc": null, "approved_by": null, "archived": false, "associated_award": null, "author": "SnooOwls8484", "author_flair_background_color": null, "author_flair_css_class": null, "author_flair_richtext": [], "author_flair_template_id": null, "author_flair_text": null, "author_flair_text_color": null, "author_flair_type": "text", "author_fullname": "t2_7kdogyh1", "author_is_blocked": false, "author_patreon_flair": false, "author_premium": false, "awarders": [], "banned_at_utc": null, "banned_by": null, "body": "Bhai mein vit se hoon hi nahi", "can_gild": false, "can_mod_post": false, "collapsed": false, "collapsed_because_crowd_control": null, "collapsed_reason": null, "collapsed_reason_code": null, "comment_type": null, "controversiality": 0, "created": 1722754480, "created_utc": 1722754480, "distinguished": null, "downs": 0, "edited": false, "gilded": 0, "gildings": {}, "id": "lgf31i7", "is_submitter": false, "likes": null, "link_id": "t3_1ehapj2", "locked": false, "mod_note": null, "mod_reason_by": null, "mod_reason_title": null, "mod_reports": [], "name": "t1_lgf31i7", "no_follow": true, "num_reports": null, "parent_id": "t1_lge639j", "permalink": "/r/Btechtards/comments/1ehapj2/tiering_of_colleges_does_not_make_any_sense/lgf31i7/", "removal_reason": null, "replies": "", "report_reasons": null, "retrieved_on": 1722754495, "saved": false, "score": 1, "score_hidden": false, "send_replies": true, "stickied": false, "subreddit": "Btechtards", "subreddit_id": "t5_56z50y", "subreddit_name_prefixed": "r/Btechtards", "subreddit_type": "public", "top_awarded_type": null, "total_awards_received": 0, "treatment_tags": [], "unrepliable_reason": null, "ups": 1, "user_reports": []}, {"_meta": {"retrieved_2nd_on": 1722867132}, "all_awardings": [], "approved_at_utc": null, "approved_by": null, "archived": false, "associated_award": null, "author": "Outside-Tadpole-5288", "author_flair_background_color": null, "author_flair_css_class": null, "author_flair_richtext": [], "author_flair_template_id": null, "author_flair_text": null, "author_flair_text_color": null, "author_flair_type": "text", "author_fullname": "t2_yi5lp70p8", "author_is_blocked": false, "author_patreon_flair": false, "author_premium": false, "awarders": [], "banned_at_utc": null, "banned_by": null, "body": "Vit kid spotted", "can_gild": false, "can_mod_post": false, "collapsed": false, "collapsed_because_crowd_control": null, "collapsed_reason": null, "collapsed_reason_code": null, "comment_type": null, "controversiality": 0, "created": 1722737503, "created_utc": 1722737503, "distinguished": null, "downs": 0, "edited": false, "gilded": 0, "gildings": {}, "id": "lge639j", "is_submitter": false, "likes": null, "link_id": "t3_1ehapj2", "locked": false, "mod_note": null, "mod_reason_by": null, "mod_reason_title": null, "mod_reports": [], "name": "t1_lge639j", "no_follow": true, "num_reports": null, "parent_id": "t1_lfz42e9", "permalink": "/r/Btechtards/comments/1ehapj2/tiering_of_colleges_does_not_make_any_sense/lge639j/", "removal_reason": null, "replies": "", "report_reasons": null, "retrieved_on": 1722737517, "saved": false, "score": 1, "score_hidden": false, "send_replies": true, "stickied": false, "subreddit": "Btechtards", "subreddit_id": "t5_56z50y", "subreddit_name_prefixed": "r/Btechtards", "subreddit_type": "public", "top_awarded_type": null, "total_awards_received": 0, "treatment_tags": [], "unrepliable_reason": null, "ups": 1, "user_reports": []}, {"_meta": {"retrieved_2nd_on": 1722867002}, "all_awardings": [], "approved_at_utc": null, "approved_by": null, "archived": false, "associated_award": null, "author": "Outside-Tadpole-5288", "author_flair_background_color": null, "author_flair_css_class": null, "author_flair_richtext": [], "author_flair_template_id": null, "author_flair_text": null, "author_flair_text_color": null, "author_flair_type": "text", "author_fullname": "t2_yi5lp70p8", "author_is_blocked": false, "author_patreon_flair": false, "author_premium": false, "awarders": [], "banned_at_utc": null, "banned_by": null, "body": "It's always kids at vit saying these things", "can_gild": false, "can_mod_post": false, "collapsed": false, "collapsed_because_crowd_control": null, "collapsed_reason": null, "collapsed_reason_code": null, "comment_type": null, "controversiality": 0, "created": 1722737393, "created_utc": 1722737393, "distinguished": null, "downs": 0, "edited": false, "gilded": 0, "gildings": {}, "id": "lge5ttg", "is_submitter": false, "likes": null, "link_id": "t3_1ehapj2", "locked": false, "mod_note": null, "mod_reason_by": null, "mod_reason_title": null, "mod_reports": [], "name": "t1_lge5ttg", "no_follow": true, "num_reports": null, "parent_id": "t1_lfz592b", "permalink": "/r/Btechtards/comments/1ehapj2/tiering_of_colleges_does_not_make_any_sense/lge5ttg/", "removal_reason": null, "replies": "", "report_reasons": null, "retrieved_on": 1722737409, "saved": false, "score": 1, "score_hidden": false, "send_replies": true, "stickied": false, "subreddit": "Btechtards", "subreddit_id": "t5_56z50y", "subreddit_name_prefixed": "r/Btechtards", "subreddit_type": "public", "top_awarded_type": null, "total_awards_received": 0, "treatment_tags": [], "unrepliable_reason": null, "ups": 1, "user_reports": []}, {"_meta": {"is_edited": true, "retrieved_2nd_on": 1722793395}, "all_awardings": [], "approved_at_utc": null, "approved_by": null, "archived": false, "associated_award": null, "author": "Isaidblahhbblah", "author_flair_background_color": null, "author_flair_css_class": null, "author_flair_richtext": [], "author_flair_template_id": null, "author_flair_text": null, "author_flair_text_color": null, "author_flair_type": "text", "author_fullname": "t2_fszll4jfx", "author_is_blocked": false, "author_patreon_flair": false, "author_premium": false, "awarders": [], "banned_at_utc": null, "banned_by": null, "body": ">Ohh got it, Thanks![img](emote|t5_56z50y|50735)![img](emote|t5_56z50y|50733)", "can_gild": false, "can_mod_post": false, "collapsed": false, "collapsed_because_crowd_control": null, "collapsed_reason": null, "collapsed_reason_code": null, "comment_type": null, "controversiality": 0, "created": 1722663784, "created_utc": 1722663784, "distinguished": null, "downs": 0, "edited": false, "gilded": 0, "gildings": {}, "id": "lg9d919", "is_submitter": false, "likes": null, "link_id": "t3_1ehapj2", "locked": false, "media_metadata": {"emote|t5_56z50y|50733": {"e": "Image", "id": "emote|t5_56z50y|50733", "m": "image/png", "s": {"u": "https://reddit-econ-prod-assets-permanent.s3.amazonaws.com/asset-manager/t5_56z50y/AHh5zyIRMx.png", "x": 20, "y": 20}, "status": "valid", "t": "emoji"}, "emote|t5_56z50y|50735": {"e": "Image", "id": "emote|t5_56z50y|50735", "m": "image/png", "s": {"u": "https://reddit-econ-prod-assets-permanent.s3.amazonaws.com/asset-manager/t5_56z50y/aCVt1cjYha.png", "x": 20, "y": 20}, "status": "valid", "t": "emoji"}}, "mod_note": null, "mod_reason_by": null, "mod_reason_title": null, "mod_reports": [], "name": "t1_lg9d919", "no_follow": true, "num_reports": null, "parent_id": "t1_lg89o7h", "permalink": "/r/Btechtards/comments/1ehapj2/tiering_of_colleges_does_not_make_any_sense/lg9d919/", "removal_reason": null, "replies": "", "report_reasons": null, "retrieved_on": 1722663799, "saved": false, "score": 1, "score_hidden": false, "send_replies": true, "stickied": false, "subreddit": "Btechtards", "subreddit_id": "t5_56z50y", "subreddit_name_prefixed": "r/Btechtards", "subreddit_type": "public", "top_awarded_type": null, "total_awards_received": 0, "treatment_tags": [], "unrepliable_reason": null, "ups": 1, "user_reports": []}, {"_meta": {"retrieved_2nd_on": 1722775183}, "all_awardings": [], "approved_at_utc": null, "approved_by": null, "archived": false, "associated_award": null, "author": "Captain_Nemo5", "author_flair_background_color": null, "author_flair_css_class": null, "author_flair_richtext": [], "author_flair_template_id": null, "author_flair_text": null, "author_flair_text_color": null, "author_flair_type": "text", "author_fullname": "t2_1qgsfwfo", "author_is_blocked": false, "author_patreon_flair": false, "author_premium": false, "awarders": [], "banned_at_utc": null, "banned_by": null, "body": "https://www.reddit.com/r/LearnToReddit/s/BrOTXzJ0kU\n\nLots to learn from here", "can_gild": false, "can_mod_post": false, "collapsed": false, "collapsed_because_crowd_control": null, "collapsed_reason": null, "collapsed_reason_code": null, "comment_type": null, "controversiality": 0, "created": 1722645574, "created_utc": 1722645574, "distinguished": null, "downs": 0, "edited": false, "gilded": 0, "gildings": {}, "id": "lg89o7h", "is_submitter": false, "likes": null, "link_id": "t3_1ehapj2", "locked": false, "mod_note": null, "mod_reason_by": null, "mod_reason_title": null, "mod_reports": [], "name": "t1_lg89o7h", "no_follow": true, "num_reports": null, "parent_id": "t1_lg1s41j", "permalink": "/r/Btechtards/comments/1ehapj2/tiering_of_colleges_does_not_make_any_sense/lg89o7h/", "removal_reason": null, "replies": "", "report_reasons": null, "retrieved_on": 1722645591, "saved": false, "score": 1, "score_hidden": false, "send_replies": true, "stickied": false, "subreddit": "Btechtards", "subreddit_id": "t5_56z50y", "subreddit_name_prefixed": "r/Btechtards", "subreddit_type": "public", "top_awarded_type": null, "total_awards_received": 0, "treatment_tags": [], "unrepliable_reason": null, "ups": 1, "user_reports": []}, {"_meta": {"retrieved_2nd_on": 1722707412}, "all_awardings": [], "approved_at_utc": null, "approved_by": null, "archived": false, "associated_award": null, "author": "YoungEducational1991", "author_flair_background_color": "#cc5289", "author_flair_css_class": null, "author_flair_richtext": [{"e": "text", "t": "[BVB] [ECE]"}], "author_flair_template_id": "910947cc-a17e-11ee-a0ae-e6bb5f57ae4f", "author_flair_text": "[BVB] [ECE]", "author_flair_text_color": "light", "author_flair_type": "richtext", "author_fullname": "t2_9mermuu9", "author_is_blocked": false, "author_patreon_flair": false, "author_premium": false, "awarders": [], "banned_at_utc": null, "banned_by": null, "body": "Yeah I am from bvb. Sorry but I don't understand Kannada", "can_gild": false, "can_mod_post": false, "collapsed": false, "collapsed_because_crowd_control": null, "collapsed_reason": null, "collapsed_reason_code": null, "comment_type": null, "controversiality": 0, "created": 1722577701, "created_utc": 1722577701, "distinguished": null, "downs": 0, "edited": false, "gilded": 0, "gildings": {}, "id": "lg3k6ep", "is_submitter": false, "likes": null, "link_id": "t3_1ehapj2", "locked": false, "mod_note": null, "mod_reason_by": null, "mod_reason_title": null, "mod_reports": [], "name": "t1_lg3k6ep", "no_follow": false, "num_reports": null, "parent_id": "t1_lg3f8ul", "permalink": "/r/Btechtards/comments/1ehapj2/tiering_of_colleges_does_not_make_any_sense/lg3k6ep/", "removal_reason": null, "replies": "", "report_reasons": null, "retrieved_on": 1722577716, "saved": false, "score": 1, "score_hidden": false, "send_replies": true, "stickied": false, "subreddit": "Btechtards", "subreddit_id": "t5_56z50y", "subreddit_name_prefixed": "r/Btechtards", "subreddit_type": "public", "top_awarded_type": null, "total_awards_received": 0, "treatment_tags": [], "unrepliable_reason": null, "ups": 1, "user_reports": []}, {"_meta": {"is_edited": true, "retrieved_2nd_on": 1722706588}, "all_awardings": [], "approved_at_utc": null, "approved_by": null, "archived": false, "associated_award": null, "author": "ReasonableBother4859", "author_flair_background_color": null, "author_flair_css_class": null, "author_flair_richtext": [], "author_flair_template_id": null, "author_flair_text": null, "author_flair_text_color": null, "author_flair_type": "text", "author_fullname": "t2_bm31jeloh", "author_is_blocked": false, "author_patreon_flair": false, "author_premium": false, "awarders": [], "banned_at_utc": null, "banned_by": null, "body": "Facts being facts \u2026 people have to realise it\n\n1. A random Guy working at a tech company is from IITB CSE, but the same companies CEO is IITKGP Metallurgy (flash back into memory about who scored how much in JEE and who choose what branch in which IIT, did it all matter?)\n\n2. Random dude flexing his alma meter on social media now works for a famous trillion dollar electronic tech company whose Founder was from Arts College dropout had considerably less knowledge on electronics but was good at ideas and management. And his current Company CEO is from Industrial engineering background (remember Industrial engineering, people took this branch after they couldn\u2019t make it to mechanical engineering)\n\n3. Some random Joe scored 24X rank in JEE took Mechanical at IITX, created a YouTube video to show his hatred for mechanical engineering citing very low placements (not some Crores worth). Should one realise that companies like Ferrari, Lamborghini, McLaren, BMW hire top notch mechanical engineers in Europe who can design the best cars, not some C/C++ coders who can design cars .. \ud83d\ude02 \n\n4in long run this IIT vs NIT Vs tier 100 colleges ego war will be over when you enter into industry and when you face the harsh reality of industry expectation. Then you\u2019ll realise that your marks were just to enter the industry that\u2019s it.", "can_gild": false, "can_mod_post": false, "collapsed": false, "collapsed_because_crowd_control": null, "collapsed_reason": null, "collapsed_reason_code": null, "comment_type": null, "controversiality": 0, "created": 1722575596, "created_utc": 1722575596, "distinguished": null, "downs": 0, "edited": false, "gilded": 0, "gildings": {}, "id": "lg3ghkp", "is_submitter": false, "likes": null, "link_id": "t3_1ehapj2", "locked": false, "mod_note": null, "mod_reason_by": null, "mod_reason_title": null, "mod_reports": [], "name": "t1_lg3ghkp", "no_follow": true, "num_reports": null, "parent_id": "t3_1ehapj2", "permalink": "/r/Btechtards/comments/1ehapj2/tiering_of_colleges_does_not_make_any_sense/lg3ghkp/", "removal_reason": null, "replies": "", "report_reasons": null, "retrieved_on": 1722575618, "saved": false, "score": 3, "score_hidden": false, "send_replies": true, "stickied": false, "subreddit": "Btechtards", "subreddit_id": "t5_56z50y", "subreddit_name_prefixed": "r/Btechtards", "subreddit_type": "public", "top_awarded_type": null, "total_awards_received": 0, "treatment_tags": [], "unrepliable_reason": null, "ups": 3, "user_reports": []}, {"_meta": {"retrieved_2nd_on": 1722705563}, "all_awardings": [], "approved_at_utc": null, "approved_by": null, "archived": false, "associated_award": null, "author": "ReasonableBother4859", "author_flair_background_color": null, "author_flair_css_class": null, "author_flair_richtext": [], "author_flair_template_id": null, "author_flair_text": null, "author_flair_text_color": null, "author_flair_type": "text", "author_fullname": "t2_bm31jeloh", "author_is_blocked": false, "author_patreon_flair": false, "author_premium": false, "awarders": [], "banned_at_utc": null, "banned_by": null, "body": "Bro you from BVB Hubli ? Kannadigara nivu?", "can_gild": false, "can_mod_post": false, "collapsed": false, "collapsed_because_crowd_control": null, "collapsed_reason": null, "collapsed_reason_code": null, "comment_type": null, "controversiality": 0, "created": 1722574913, "created_utc": 1722574913, "distinguished": null, "downs": 0, "edited": false, "gilded": 0, "gildings": {}, "id": "lg3f8ul", "is_submitter": false, "likes": null, "link_id": "t3_1ehapj2", "locked": false, "mod_note": null, "mod_reason_by": null, "mod_reason_title": null, "mod_reports": [], "name": "t1_lg3f8ul", "no_follow": true, "num_reports": null, "parent_id": "t1_lfz592b", "permalink": "/r/Btechtards/comments/1ehapj2/tiering_of_colleges_does_not_make_any_sense/lg3f8ul/", "removal_reason": null, "replies": "", "report_reasons": null, "retrieved_on": 1722574927, "saved": false, "score": 1, "score_hidden": false, "send_replies": true, "stickied": false, "subreddit": "Btechtards", "subreddit_id": "t5_56z50y", "subreddit_name_prefixed": "r/Btechtards", "subreddit_type": "public", "top_awarded_type": null, "total_awards_received": 0, "treatment_tags": [], "unrepliable_reason": null, "ups": 1, "user_reports": []}, {"_meta": {"retrieved_2nd_on": 1722688358}, "all_awardings": [], "approved_at_utc": null, "approved_by": null, "archived": false, "associated_award": null, "author": "Cold-Comedian1166", "author_flair_background_color": null, "author_flair_css_class": null, "author_flair_richtext": [], "author_flair_template_id": null, "author_flair_text": null, "author_flair_text_color": null, "author_flair_type": "text", "author_fullname": "t2_5y7d02zir", "author_is_blocked": false, "author_patreon_flair": false, "author_premium": false, "awarders": [], "banned_at_utc": null, "banned_by": null, "body": "Kaun si NIT?", "can_gild": false, "can_mod_post": false, "collapsed": false, "collapsed_because_crowd_control": null, "collapsed_reason": null, "collapsed_reason_code": null, "comment_type": null, "controversiality": 0, "created": 1722558735, "created_utc": 1722558735, "distinguished": null, "downs": 0, "edited": false, "gilded": 0, "gildings": {}, "id": "lg2dnkj", "is_submitter": false, "likes": null, "link_id": "t3_1ehapj2", "locked": false, "mod_note": null, "mod_reason_by": null, "mod_reason_title": null, "mod_reports": [], "name": "t1_lg2dnkj", "no_follow": true, "num_reports": null, "parent_id": "t1_lfy8y5a", "permalink": "/r/Btechtards/comments/1ehapj2/tiering_of_colleges_does_not_make_any_sense/lg2dnkj/", "removal_reason": null, "replies": "", "report_reasons": null, "retrieved_on": 1722558752, "saved": false, "score": 2, "score_hidden": false, "send_replies": true, "stickied": false, "subreddit": "Btechtards", "subreddit_id": "t5_56z50y", "subreddit_name_prefixed": "r/Btechtards", "subreddit_type": "public", "top_awarded_type": null, "total_awards_received": 0, "treatment_tags": [], "unrepliable_reason": null, "ups": 2, "user_reports": []}, {"_meta": {"retrieved_2nd_on": 1722680393}, "all_awardings": [], "approved_at_utc": null, "approved_by": null, "archived": false, "associated_award": null, "author": "Isaidblahhbblah", "author_flair_background_color": null, "author_flair_css_class": null, "author_flair_richtext": [], "author_flair_template_id": null, "author_flair_text": null, "author_flair_text_color": null, "author_flair_type": "text", "author_fullname": "t2_fszll4jfx", "author_is_blocked": false, "author_patreon_flair": false, "author_premium": false, "awarders": [], "banned_at_utc": null, "banned_by": null, "body": "Haan paar feature kya hai...teach the noobs.", "can_gild": false, "can_mod_post": false, "collapsed": false, "collapsed_because_crowd_control": null, "collapsed_reason": null, "collapsed_reason_code": null, "comment_type": null, "controversiality": 0, "created": 1722550787, "created_utc": 1722550787, "distinguished": null, "downs": 0, "edited": false, "gilded": 0, "gildings": {}, "id": "lg1s41j", "is_submitter": false, "likes": null, "link_id": "t3_1ehapj2", "locked": false, "mod_note": null, "mod_reason_by": null, "mod_reason_title": null, "mod_reports": [], "name": "t1_lg1s41j", "no_follow": true, "num_reports": null, "parent_id": "t1_lfzwwp7", "permalink": "/r/Btechtards/comments/1ehapj2/tiering_of_colleges_does_not_make_any_sense/lg1s41j/", "removal_reason": null, "replies": "", "report_reasons": null, "retrieved_on": 1722550804, "saved": false, "score": 2, "score_hidden": false, "send_replies": true, "stickied": false, "subreddit": "Btechtards", "subreddit_id": "t5_56z50y", "subreddit_name_prefixed": "r/Btechtards", "subreddit_type": "public", "top_awarded_type": null, "total_awards_received": 0, "treatment_tags": [], "unrepliable_reason": null, "ups": 2, "user_reports": []}, {"_meta": {"retrieved_2nd_on": 1722673258}, "all_awardings": [], "approved_at_utc": null, "approved_by": null, "archived": false, "associated_award": null, "author": "SwashbucklingAntler", "author_flair_background_color": "#ffd635", "author_flair_css_class": null, "author_flair_richtext": [{"e": "text", "t": "BITSian EEE"}], "author_flair_template_id": "8c3340d8-4c6e-11ed-ae66-3a0a55bc7818", "author_flair_text": "BITSian EEE", "author_flair_text_color": "dark", "author_flair_type": "richtext", "author_fullname": "t2_7pvrzmal", "author_is_blocked": false, "author_patreon_flair": false, "author_premium": false, "awarders": [], "banned_at_utc": null, "banned_by": null, "body": "5th NIT (probably Rourkela) is NOT better than IITH/BHU (whichever you consider 9th), it's worse by a mile. All 2nd gen IITs>4th and 5th NIT except maybe bhubaneshwar and ropar.\n\nThere are lots of other problems with this but this one was the most glaring", "can_gild": false, "can_mod_post": false, "collapsed": false, "collapsed_because_crowd_control": null, "collapsed_reason": null, "collapsed_reason_code": null, "comment_type": null, "controversiality": 0, "created": 1722543645, "created_utc": 1722543645, "distinguished": null, "downs": 0, "edited": false, "gilded": 0, "gildings": {}, "id": "lg16a0e", "is_submitter": false, "likes": null, "link_id": "t3_1ehapj2", "locked": false, "mod_note": null, "mod_reason_by": null, "mod_reason_title": null, "mod_reports": [], "name": "t1_lg16a0e", "no_follow": true, "num_reports": null, "parent_id": "t1_lg0dep7", "permalink": "/r/Btechtards/comments/1ehapj2/tiering_of_colleges_does_not_make_any_sense/lg16a0e/", "removal_reason": null, "replies": "", "report_reasons": null, "retrieved_on": 1722543661, "saved": false, "score": 2, "score_hidden": false, "send_replies": true, "stickied": false, "subreddit": "Btechtards", "subreddit_id": "t5_56z50y", "subreddit_name_prefixed": "r/Btechtards", "subreddit_type": "public", "top_awarded_type": null, "total_awards_received": 0, "treatment_tags": [], "unrepliable_reason": null, "ups": 2, "user_reports": []}, {"_meta": {"retrieved_2nd_on": 1722671818}, "all_awardings": [], "approved_at_utc": null, "approved_by": null, "archived": false, "associated_award": null, "author": "Independent-World165", "author_flair_background_color": null, "author_flair_css_class": null, "author_flair_richtext": [], "author_flair_template_id": null, "author_flair_text": null, "author_flair_text_color": null, "author_flair_type": "text", "author_fullname": "t2_9hzz8mf0", "author_is_blocked": false, "author_patreon_flair": false, "author_premium": false, "awarders": [], "banned_at_utc": null, "banned_by": null, "body": "Bhai I belong to the 8th ranked IIT, and it is a new IIT. Placements are equivalent to number 6 and 7(roorkee and guwahati).\n\nBut obviously we are looked down upon as it's new gen IIT. Even though our campus is both bigger and better than Delhi and Mumbai combined.", "can_gild": false, "can_mod_post": false, "collapsed": false, "collapsed_because_crowd_control": null, "collapsed_reason": null, "collapsed_reason_code": null, "comment_type": null, "controversiality": 0, "created": 1722542200, "created_utc": 1722542200, "distinguished": null, "downs": 0, "edited": false, "gilded": 0, "gildings": {}, "id": "lg11i32", "is_submitter": false, "likes": null, "link_id": "t3_1ehapj2", "locked": false, "mod_note": null, "mod_reason_by": null, "mod_reason_title": null, "mod_reports": [], "name": "t1_lg11i32", "no_follow": true, "num_reports": null, "parent_id": "t1_lg0dep7", "permalink": "/r/Btechtards/comments/1ehapj2/tiering_of_colleges_does_not_make_any_sense/lg11i32/", "removal_reason": null, "replies": "", "report_reasons": null, "retrieved_on": 1722542217, "saved": false, "score": 3, "score_hidden": false, "send_replies": true, "stickied": false, "subreddit": "Btechtards", "subreddit_id": "t5_56z50y", "subreddit_name_prefixed": "r/Btechtards", "subreddit_type": "public", "top_awarded_type": null, "total_awards_received": 0, "treatment_tags": [], "unrepliable_reason": null, "ups": 3, "user_reports": []}, {"_meta": {"retrieved_2nd_on": 1722666952}, "all_awardings": [], "approved_at_utc": null, "approved_by": null, "archived": false, "associated_award": null, "author": "[deleted]", "author_flair_background_color": "", "author_flair_css_class": null, "author_flair_template_id": null, "author_flair_text": null, "author_flair_text_color": "dark", "author_is_blocked": false, "awarders": [], "banned_at_utc": null, "banned_by": null, "body": "[removed]", "can_gild": false, "can_mod_post": false, "collapsed": false, "collapsed_because_crowd_control": null, "collapsed_reason": null, "collapsed_reason_code": null, "comment_type": null, "controversiality": 0, "created": 1722537337, "created_utc": 1722537337, "distinguished": null, "downs": 0, "edited": false, "gilded": 0, "gildings": {}, "id": "lg0m1ws", "is_submitter": false, "likes": null, "link_id": "t3_1ehapj2", "locked": false, "mod_note": null, "mod_reason_by": null, "mod_reason_title": null, "mod_reports": [], "name": "t1_lg0m1ws", "no_follow": true, "num_reports": null, "parent_id": "t1_lg0dep7", "permalink": "/r/Btechtards/comments/1ehapj2/tiering_of_colleges_does_not_make_any_sense/lg0m1ws/", "removal_reason": null, "replies": "", "report_reasons": null, "retrieved_on": 1722537356, "saved": false, "score": 1, "score_hidden": false, "send_replies": true, "stickied": false, "subreddit": "Btechtards", "subreddit_id": "t5_56z50y", "subreddit_name_prefixed": "r/Btechtards", "subreddit_type": "public", "top_awarded_type": null, "total_awards_received": 0, "treatment_tags": [], "unrepliable_reason": null, "ups": 1, "user_reports": []}, {"_meta": {"retrieved_2nd_on": 1722664280}, "all_awardings": [], "approved_at_utc": null, "approved_by": null, "archived": false, "associated_award": null, "author": "Familiar-Cat3753", "author_flair_background_color": null, "author_flair_css_class": null, "author_flair_richtext": [], "author_flair_template_id": null, "author_flair_text": null, "author_flair_text_color": null, "author_flair_type": "text", "author_fullname": "t2_vn91jokl", "author_is_blocked": false, "author_patreon_flair": false, "author_premium": false, "awarders": [], "banned_at_utc": null, "banned_by": null, "body": "It's true MIT is tier 2 \n\n\nOnly Tier 1 colleges are top 8 IITS, TOP 5 NITs , Top 4 IIITs, Jadavpur University and BITS Pilani main campus", "can_gild": false, "can_mod_post": false, "collapsed": false, "collapsed_because_crowd_control": null, "collapsed_reason": null, "collapsed_reason_code": null, "comment_type": null, "controversiality": 0, "created": 1722534670, "created_utc": 1722534670, "distinguished": null, "downs": 0, "edited": false, "gilded": 0, "gildings": {}, "id": "lg0dep7", "is_submitter": false, "likes": null, "link_id": "t3_1ehapj2", "locked": false, "mod_note": null, "mod_reason_by": null, "mod_reason_title": null, "mod_reports": [], "name": "t1_lg0dep7", "no_follow": true, "num_reports": null, "parent_id": "t3_1ehapj2", "permalink": "/r/Btechtards/comments/1ehapj2/tiering_of_colleges_does_not_make_any_sense/lg0dep7/", "removal_reason": null, "replies": "", "report_reasons": null, "retrieved_on": 1722534687, "saved": false, "score": -3, "score_hidden": false, "send_replies": true, "stickied": false, "subreddit": "Btechtards", "subreddit_id": "t5_56z50y", "subreddit_name_prefixed": "r/Btechtards", "subreddit_type": "public", "top_awarded_type": null, "total_awards_received": 0, "treatment_tags": [], "unrepliable_reason": null, "ups": -3, "user_reports": []}, {"_meta": {"retrieved_2nd_on": 1722659541}, "all_awardings": [], "approved_at_utc": null, "approved_by": null, "archived": false, "associated_award": null, "author": "dorkydora20", "author_flair_background_color": "#cc5289", "author_flair_css_class": null, "author_flair_richtext": [{"e": "text", "t": "kabootar science enjoyer"}], "author_flair_template_id": "910947cc-a17e-11ee-a0ae-e6bb5f57ae4f", "author_flair_text": "kabootar science enjoyer", "author_flair_text_color": "light", "author_flair_type": "richtext", "author_fullname": "t2_jjp6vvrkc", "author_is_blocked": false, "author_patreon_flair": false, "author_premium": false, "awarders": [], "banned_at_utc": null, "banned_by": null, "body": "zyada tier tier krne vle tyre ghumate rehjate hain, jinhone kuch acha kia hota hai unhe brag krne ki zarurat nahi pdti, this all is bs imo", "can_gild": false, "can_mod_post": false, "collapsed": false, "collapsed_because_crowd_control": null, "collapsed_reason": null, "collapsed_reason_code": null, "comment_type": null, "controversiality": 0, "created": 1722529935, "created_utc": 1722529935, "distinguished": null, "downs": 0, "edited": false, "gilded": 0, "gildings": {}, "id": "lfzy7qj", "is_submitter": false, "likes": null, "link_id": "t3_1ehapj2", "locked": false, "mod_note": null, "mod_reason_by": null, "mod_reason_title": null, "mod_reports": [], "name": "t1_lfzy7qj", "no_follow": true, "num_reports": null, "parent_id": "t3_1ehapj2", "permalink": "/r/Btechtards/comments/1ehapj2/tiering_of_colleges_does_not_make_any_sense/lfzy7qj/", "removal_reason": null, "replies": "", "report_reasons": null, "retrieved_on": 1722529952, "saved": false, "score": 1, "score_hidden": false, "send_replies": true, "stickied": false, "subreddit": "Btechtards", "subreddit_id": "t5_56z50y", "subreddit_name_prefixed": "r/Btechtards", "subreddit_type": "public", "top_awarded_type": null, "total_awards_received": 0, "treatment_tags": [], "unrepliable_reason": null, "ups": 1, "user_reports": []}, {"_meta": {"retrieved_2nd_on": 1722659141}, "all_awardings": [], "approved_at_utc": null, "approved_by": null, "archived": false, "associated_award": null, "author": "serious-aspirant", "author_flair_background_color": null, "author_flair_css_class": null, "author_flair_richtext": [], "author_flair_template_id": null, "author_flair_text": null, "author_flair_text_color": null, "author_flair_type": "text", "author_fullname": "t2_uw1jewng", "author_is_blocked": false, "author_patreon_flair": false, "author_premium": false, "awarders": [], "banned_at_utc": null, "banned_by": null, "body": "> ese", "can_gild": false, "can_mod_post": false, "collapsed": false, "collapsed_because_crowd_control": null, "collapsed_reason": null, "collapsed_reason_code": null, "comment_type": null, "controversiality": 0, "created": 1722529527, "created_utc": 1722529527, "distinguished": null, "downs": 0, "edited": false, "gilded": 0, "gildings": {}, "id": "lfzwwp7", "is_submitter": false, "likes": null, "link_id": "t3_1ehapj2", "locked": false, "mod_note": null, "mod_reason_by": null, "mod_reason_title": null, "mod_reports": [], "name": "t1_lfzwwp7", "no_follow": true, "num_reports": null, "parent_id": "t1_lfzgjfv", "permalink": "/r/Btechtards/comments/1ehapj2/tiering_of_colleges_does_not_make_any_sense/lfzwwp7/", "removal_reason": null, "replies": "", "report_reasons": null, "retrieved_on": 1722529544, "saved": false, "score": 3, "score_hidden": false, "send_replies": true, "stickied": false, "subreddit": "Btechtards", "subreddit_id": "t5_56z50y", "subreddit_name_prefixed": "r/Btechtards", "subreddit_type": "public", "top_awarded_type": null, "total_awards_received": 0, "treatment_tags": [], "unrepliable_reason": null, "ups": 3, "user_reports": []}, {"_meta": {"retrieved_2nd_on": 1722658684}, "all_awardings": [], "approved_at_utc": null, "approved_by": null, "archived": false, "associated_award": null, "author": "Adept-Ice8074", "author_flair_background_color": null, "author_flair_css_class": null, "author_flair_richtext": [], "author_flair_template_id": null, "author_flair_text": null, "author_flair_text_color": null, "author_flair_type": "text", "author_fullname": "t2_xxyn5dgzv", "author_is_blocked": false, "author_patreon_flair": false, "author_premium": false, "awarders": [], "banned_at_utc": null, "banned_by": null, "body": "Real", "can_gild": false, "can_mod_post": false, "collapsed": false, "collapsed_because_crowd_control": null, "collapsed_reason": null, "collapsed_reason_code": null, "comment_type": null, "controversiality": 0, "created": 1722529072, "created_utc": 1722529072, "distinguished": null, "downs": 0, "edited": false, "gilded": 0, "gildings": {}, "id": "lfzvh6n", "is_submitter": false, "likes": null, "link_id": "t3_1ehapj2", "locked": false, "mod_note": null, "mod_reason_by": null, "mod_reason_title": null, "mod_reports": [], "name": "t1_lfzvh6n", "no_follow": true, "num_reports": null, "parent_id": "t1_lfzk2io", "permalink": "/r/Btechtards/comments/1ehapj2/tiering_of_colleges_does_not_make_any_sense/lfzvh6n/", "removal_reason": null, "replies": "", "report_reasons": null, "retrieved_on": 1722529087, "saved": false, "score": 2, "score_hidden": false, "send_replies": true, "stickied": false, "subreddit": "Btechtards", "subreddit_id": "t5_56z50y", "subreddit_name_prefixed": "r/Btechtards", "subreddit_type": "public", "top_awarded_type": null, "total_awards_received": 0, "treatment_tags": [], "unrepliable_reason": null, "ups": 2, "user_reports": []}, {"_meta": {"retrieved_2nd_on": 1722655836}, "all_awardings": [], "approved_at_utc": null, "approved_by": null, "archived": false, "associated_award": null, "author": "SimplyPabloBack", "author_flair_background_color": "transparent", "author_flair_css_class": null, "author_flair_richtext": [{"e": "text", "t": "[DTU]"}], "author_flair_template_id": "b9a8ed0c-b616-11ee-a29a-fe10775cecf8", "author_flair_text": "[DTU]", "author_flair_text_color": "dark", "author_flair_type": "richtext", "author_fullname": "t2_1501ud4k6l", "author_is_blocked": false, "author_patreon_flair": false, "author_premium": false, "awarders": [], "banned_at_utc": null, "banned_by": null, "body": "Someone called your college tier 2 or 3 right?", "can_gild": false, "can_mod_post": false, "collapsed": false, "collapsed_because_crowd_control": null, "collapsed_reason": null, "collapsed_reason_code": null, "comment_type": null, "controversiality": 0, "created": 1722526224, "created_utc": 1722526224, "distinguished": null, "downs": 0, "edited": false, "gilded": 0, "gildings": {}, "id": "lfzmi6m", "is_submitter": false, "likes": null, "link_id": "t3_1ehapj2", "locked": false, "mod_note": null, "mod_reason_by": null, "mod_reason_title": null, "mod_reports": [], "name": "t1_lfzmi6m", "no_follow": true, "num_reports": null, "parent_id": "t3_1ehapj2", "permalink": "/r/Btechtards/comments/1ehapj2/tiering_of_colleges_does_not_make_any_sense/lfzmi6m/", "removal_reason": null, "replies": "", "report_reasons": null, "retrieved_on": 1722526242, "saved": false, "score": 3, "score_hidden": false, "send_replies": true, "stickied": false, "subreddit": "Btechtards", "subreddit_id": "t5_56z50y", "subreddit_name_prefixed": "r/Btechtards", "subreddit_type": "public", "top_awarded_type": null, "total_awards_received": 0, "treatment_tags": [], "unrepliable_reason": null, "ups": 3, "user_reports": []}, {"_meta": {"retrieved_2nd_on": 1722655054}, "all_awardings": [], "approved_at_utc": null, "approved_by": null, "archived": false, "associated_award": null, "author": "Loner_0112", "author_flair_background_color": null, "author_flair_css_class": null, "author_flair_richtext": [], "author_flair_template_id": null, "author_flair_text": null, "author_flair_text_color": null, "author_flair_type": "text", "author_fullname": "t2_mifyyn7u", "author_is_blocked": false, "author_patreon_flair": false, "author_premium": false, "awarders": [], "banned_at_utc": null, "banned_by": null, "body": "Kyuki tune baccho ko 4 saal toda hai", "can_gild": false, "can_mod_post": false, "collapsed": false, "collapsed_because_crowd_control": null, "collapsed_reason": null, "collapsed_reason_code": null, "comment_type": null, "controversiality": 0, "created": 1722525446, "created_utc": 1722525446, "distinguished": null, "downs": 0, "edited": false, "gilded": 0, "gildings": {}, "id": "lfzk2io", "is_submitter": false, "likes": null, "link_id": "t3_1ehapj2", "locked": false, "mod_note": null, "mod_reason_by": null, "mod_reason_title": null, "mod_reports": [], "name": "t1_lfzk2io", "no_follow": true, "num_reports": null, "parent_id": "t1_lfy8y5a", "permalink": "/r/Btechtards/comments/1ehapj2/tiering_of_colleges_does_not_make_any_sense/lfzk2io/", "removal_reason": null, "replies": "", "report_reasons": null, "retrieved_on": 1722525462, "saved": false, "score": 7, "score_hidden": false, "send_replies": true, "stickied": false, "subreddit": "Btechtards", "subreddit_id": "t5_56z50y", "subreddit_name_prefixed": "r/Btechtards", "subreddit_type": "public", "top_awarded_type": null, "total_awards_received": 0, "treatment_tags": [], "unrepliable_reason": null, "ups": 7, "user_reports": []}, {"_meta": {"retrieved_2nd_on": 1722653908}, "all_awardings": [], "approved_at_utc": null, "approved_by": null, "archived": false, "associated_award": null, "author": "itachithegreat", "author_flair_background_color": null, "author_flair_css_class": null, "author_flair_richtext": [], "author_flair_template_id": null, "author_flair_text": null, "author_flair_text_color": null, "author_flair_type": "text", "author_fullname": "t2_cnv9u5a8", "author_is_blocked": false, "author_patreon_flair": false, "author_premium": false, "awarders": [], "banned_at_utc": null, "banned_by": null, "body": "Bhai ye kaise kiya upar me ye line kaise likha", "can_gild": false, "can_mod_post": false, "collapsed": false, "collapsed_because_crowd_control": null, "collapsed_reason": null, "collapsed_reason_code": null, "comment_type": null, "controversiality": 0, "created": 1722524296, "created_utc": 1722524296, "distinguished": null, "downs": 0, "edited": false, "gilded": 0, "gildings": {}, "id": "lfzgjfv", "is_submitter": false, "likes": null, "link_id": "t3_1ehapj2", "locked": false, "mod_note": null, "mod_reason_by": null, "mod_reason_title": null, "mod_reports": [], "name": "t1_lfzgjfv", "no_follow": true, "num_reports": null, "parent_id": "t1_lfy8iul", "permalink": "/r/Btechtards/comments/1ehapj2/tiering_of_colleges_does_not_make_any_sense/lfzgjfv/", "removal_reason": null, "replies": "", "report_reasons": null, "retrieved_on": 1722524311, "saved": false, "score": 3, "score_hidden": false, "send_replies": true, "stickied": false, "subreddit": "Btechtards", "subreddit_id": "t5_56z50y", "subreddit_name_prefixed": "r/Btechtards", "subreddit_type": "public", "top_awarded_type": null, "total_awards_received": 0, "treatment_tags": [], "unrepliable_reason": null, "ups": 3, "user_reports": []}, {"_meta": {"retrieved_2nd_on": 1722650102}, "all_awardings": [], "approved_at_utc": null, "approved_by": null, "archived": false, "associated_award": null, "author": "YoungEducational1991", "author_flair_background_color": "#cc5289", "author_flair_css_class": null, "author_flair_richtext": [{"e": "text", "t": "[BVB] [ECE]"}], "author_flair_template_id": "910947cc-a17e-11ee-a0ae-e6bb5f57ae4f", "author_flair_text": "[BVB] [ECE]", "author_flair_text_color": "light", "author_flair_type": "richtext", "author_fullname": "t2_9mermuu9", "author_is_blocked": false, "author_patreon_flair": false, "author_premium": false, "awarders": [], "banned_at_utc": null, "banned_by": null, "body": "It's always vit in the crime scene", "can_gild": false, "can_mod_post": false, "collapsed": false, "collapsed_because_crowd_control": null, "collapsed_reason": null, "collapsed_reason_code": null, "comment_type": null, "controversiality": 0, "created": 1722520489, "created_utc": 1722520489, "distinguished": null, "downs": 0, "edited": false, "gilded": 0, "gildings": {}, "id": "lfz592b", "is_submitter": false, "likes": null, "link_id": "t3_1ehapj2", "locked": false, "mod_note": null, "mod_reason_by": null, "mod_reason_title": null, "mod_reports": [], "name": "t1_lfz592b", "no_follow": true, "num_reports": null, "parent_id": "t3_1ehapj2", "permalink": "/r/Btechtards/comments/1ehapj2/tiering_of_colleges_does_not_make_any_sense/lfz592b/", "removal_reason": null, "replies": "", "report_reasons": null, "retrieved_on": 1722520505, "saved": false, "score": 16, "score_hidden": false, "send_replies": true, "stickied": false, "subreddit": "Btechtards", "subreddit_id": "t5_56z50y", "subreddit_name_prefixed": "r/Btechtards", "subreddit_type": "public", "top_awarded_type": null, "total_awards_received": 0, "treatment_tags": [], "unrepliable_reason": null, "ups": 16, "user_reports": []}, {"_meta": {"retrieved_2nd_on": 1722649677}, "all_awardings": [], "approved_at_utc": null, "approved_by": null, "archived": false, "associated_award": null, "author": "SnooOwls8484", "author_flair_background_color": null, "author_flair_css_class": null, "author_flair_richtext": [], "author_flair_template_id": null, "author_flair_text": null, "author_flair_text_color": null, "author_flair_type": "text", "author_fullname": "t2_7kdogyh1", "author_is_blocked": false, "author_patreon_flair": false, "author_premium": false, "awarders": [], "banned_at_utc": null, "banned_by": null, "body": "This is a tier 2 post", "can_gild": false, "can_mod_post": false, "collapsed": false, "collapsed_because_crowd_control": null, "collapsed_reason": null, "collapsed_reason_code": null, "comment_type": null, "controversiality": 0, "created": 1722520066, "created_utc": 1722520066, "distinguished": null, "downs": 0, "edited": false, "gilded": 0, "gildings": {}, "id": "lfz42e9", "is_submitter": false, "likes": null, "link_id": "t3_1ehapj2", "locked": false, "mod_note": null, "mod_reason_by": null, "mod_reason_title": null, "mod_reports": [], "name": "t1_lfz42e9", "no_follow": true, "num_reports": null, "parent_id": "t3_1ehapj2", "permalink": "/r/Btechtards/comments/1ehapj2/tiering_of_colleges_does_not_make_any_sense/lfz42e9/", "removal_reason": null, "replies": "", "report_reasons": null, "retrieved_on": 1722520082, "saved": false, "score": 7, "score_hidden": false, "send_replies": true, "stickied": false, "subreddit": "Btechtards", "subreddit_id": "t5_56z50y", "subreddit_name_prefixed": "r/Btechtards", "subreddit_type": "public", "top_awarded_type": null, "total_awards_received": 0, "treatment_tags": [], "unrepliable_reason": null, "ups": 7, "user_reports": []}, {"_meta": {"retrieved_2nd_on": 1722648410}, "all_awardings": [], "approved_at_utc": null, "approved_by": null, "archived": false, "associated_award": null, "author": "TECH_INFRARED", "author_flair_background_color": null, "author_flair_css_class": null, "author_flair_richtext": [], "author_flair_template_id": null, "author_flair_text": null, "author_flair_text_color": null, "author_flair_type": "text", "author_fullname": "t2_vm3y4kfo0", "author_is_blocked": false, "author_patreon_flair": false, "author_premium": false, "awarders": [], "banned_at_utc": null, "banned_by": null, "body": "Mere liye dream college tier 1 aur baaki sab tier 2 and that's it", "can_gild": false, "can_mod_post": false, "collapsed": false, "collapsed_because_crowd_control": null, "collapsed_reason": null, "collapsed_reason_code": null, "comment_type": null, "controversiality": 0, "created": 1722518790, "created_utc": 1722518790, "distinguished": null, "downs": 0, "edited": false, "gilded": 0, "gildings": {}, "id": "lfz0mt7", "is_submitter": false, "likes": null, "link_id": "t3_1ehapj2", "locked": false, "mod_note": null, "mod_reason_by": null, "mod_reason_title": null, "mod_reports": [], "name": "t1_lfz0mt7", "no_follow": false, "num_reports": null, "parent_id": "t3_1ehapj2", "permalink": "/r/Btechtards/comments/1ehapj2/tiering_of_colleges_does_not_make_any_sense/lfz0mt7/", "removal_reason": null, "replies": "", "report_reasons": null, "retrieved_on": 1722518807, "saved": false, "score": 3, "score_hidden": false, "send_replies": true, "stickied": false, "subreddit": "Btechtards", "subreddit_id": "t5_56z50y", "subreddit_name_prefixed": "r/Btechtards", "subreddit_type": "public", "top_awarded_type": null, "total_awards_received": 0, "treatment_tags": [], "unrepliable_reason": null, "ups": 3, "user_reports": []}, {"_meta": {"retrieved_2nd_on": 1722646212}, "all_awardings": [], "approved_at_utc": null, "approved_by": null, "archived": false, "associated_award": null, "author": "ancient_armor", "author_flair_background_color": null, "author_flair_css_class": null, "author_flair_richtext": [], "author_flair_template_id": null, "author_flair_text": null, "author_flair_text_color": null, "author_flair_type": "text", "author_fullname": "t2_7qpb1180", "author_is_blocked": false, "author_patreon_flair": false, "author_premium": false, "awarders": [], "banned_at_utc": null, "banned_by": null, "body": "Tier 3 wale sare apna copium le rhe h", "can_gild": false, "can_mod_post": false, "collapsed": false, "collapsed_because_crowd_control": null, "collapsed_reason": null, "collapsed_reason_code": null, "comment_type": null, "controversiality": 0, "created": 1722516599, "created_utc": 1722516599, "distinguished": null, "downs": 0, "edited": false, "gilded": 0, "gildings": {}, "id": "lfyv2jm", "is_submitter": false, "likes": null, "link_id": "t3_1ehapj2", "locked": false, "mod_note": null, "mod_reason_by": null, "mod_reason_title": null, "mod_reports": [], "name": "t1_lfyv2jm", "no_follow": true, "num_reports": null, "parent_id": "t3_1ehapj2", "permalink": "/r/Btechtards/comments/1ehapj2/tiering_of_colleges_does_not_make_any_sense/lfyv2jm/", "removal_reason": null, "replies": "", "report_reasons": null, "retrieved_on": 1722516613, "saved": false, "score": 3, "score_hidden": false, "send_replies": true, "stickied": false, "subreddit": "Btechtards", "subreddit_id": "t5_56z50y", "subreddit_name_prefixed": "r/Btechtards", "subreddit_type": "public", "top_awarded_type": null, "total_awards_received": 0, "treatment_tags": [], "unrepliable_reason": null, "ups": 3, "user_reports": []}, {"_meta": {"retrieved_2nd_on": 1722642833}, "all_awardings": [], "approved_at_utc": null, "approved_by": null, "archived": false, "associated_award": null, "author": "Athiktos-", "author_flair_background_color": "#cc5289", "author_flair_css_class": null, "author_flair_richtext": [{"e": "text", "t": " [CSE - Non Binary]"}], "author_flair_template_id": "910947cc-a17e-11ee-a0ae-e6bb5f57ae4f", "author_flair_text": " [CSE - Non Binary]", "author_flair_text_color": "light", "author_flair_type": "richtext", "author_fullname": "t2_10q7cbjs5c", "author_is_blocked": false, "author_patreon_flair": false, "author_premium": false, "awarders": [], "banned_at_utc": null, "banned_by": null, "body": "koi na", "can_gild": false, "can_mod_post": false, "collapsed": false, "collapsed_because_crowd_control": null, "collapsed_reason": null, "collapsed_reason_code": null, "comment_type": null, "controversiality": 0, "created": 1722513223, "created_utc": 1722513223, "distinguished": null, "downs": 0, "edited": false, "gilded": 0, "gildings": {}, "id": "lfyngb2", "is_submitter": false, "likes": null, "link_id": "t3_1ehapj2", "locked": false, "mod_note": null, "mod_reason_by": null, "mod_reason_title": null, "mod_reports": [], "name": "t1_lfyngb2", "no_follow": true, "num_reports": null, "parent_id": "t1_lfybes5", "permalink": "/r/Btechtards/comments/1ehapj2/tiering_of_colleges_does_not_make_any_sense/lfyngb2/", "removal_reason": null, "replies": "", "report_reasons": null, "retrieved_on": 1722513237, "saved": false, "score": 0, "score_hidden": false, "send_replies": true, "stickied": false, "subreddit": "Btechtards", "subreddit_id": "t5_56z50y", "subreddit_name_prefixed": "r/Btechtards", "subreddit_type": "public", "top_awarded_type": null, "total_awards_received": 0, "treatment_tags": [], "unrepliable_reason": null, "ups": 0, "user_reports": []}, {"_meta": {"is_edited": true, "retrieved_2nd_on": 1722640313}, "all_awardings": [], "approved_at_utc": null, "approved_by": null, "archived": false, "associated_award": null, "author": "The_6699_Guy", "author_flair_background_color": null, "author_flair_css_class": null, "author_flair_richtext": [], "author_flair_template_id": null, "author_flair_text": null, "author_flair_text_color": null, "author_flair_type": "text", "author_fullname": "t2_9c8aqe1y", "author_is_blocked": false, "author_patreon_flair": false, "author_premium": false, "awarders": [], "banned_at_utc": null, "banned_by": null, "body": "it is the type of thing which should be frowned upon but is still somehow become a norm even among those are against this 'tiering'. \n\nIf a person in a well reputed college will say this to stop tier building of colleges, others in not so reputed college with make him believe otherwise even if it means admitting their college is a tier or 2 lower than the 1st person's college.\n\nAnd if the scenario reverses, others will drag him/her down saying the person is inflating his ego by not admitting their college is tier2/3. \n\nWhich leads us to people either being boastful about their college ''tier' or ones being much harsher with their 'tier criteria' and going around saying tier69 and shit. And then a good chunk lies in the middle ground going along with this because trying to remove this tier mentality is much harder than it looks.", "can_gild": false, "can_mod_post": false, "collapsed": false, "collapsed_because_crowd_control": null, "collapsed_reason": null, "collapsed_reason_code": null, "comment_type": null, "controversiality": 0, "created": 1722510702, "created_utc": 1722510702, "distinguished": null, "downs": 0, "edited": false, "gilded": 0, "gildings": {}, "id": "lfyifm2", "is_submitter": false, "likes": null, "link_id": "t3_1ehapj2", "locked": false, "mod_note": null, "mod_reason_by": null, "mod_reason_title": null, "mod_reports": [], "name": "t1_lfyifm2", "no_follow": true, "num_reports": null, "parent_id": "t3_1ehapj2", "permalink": "/r/Btechtards/comments/1ehapj2/tiering_of_colleges_does_not_make_any_sense/lfyifm2/", "removal_reason": null, "replies": "", "report_reasons": null, "retrieved_on": 1722510716, "saved": false, "score": 8, "score_hidden": false, "send_replies": true, "stickied": false, "subreddit": "Btechtards", "subreddit_id": "t5_56z50y", "subreddit_name_prefixed": "r/Btechtards", "subreddit_type": "public", "top_awarded_type": null, "total_awards_received": 0, "treatment_tags": [], "unrepliable_reason": null, "ups": 8, "user_reports": []}, {"_meta": {"is_edited": true, "retrieved_2nd_on": 1722636409}, "all_awardings": [], "approved_at_utc": null, "approved_by": null, "archived": false, "associated_award": null, "author": "Super-Professor-3457", "author_flair_background_color": null, "author_flair_css_class": null, "author_flair_richtext": [], "author_flair_template_id": null, "author_flair_text": null, "author_flair_text_color": null, "author_flair_type": "text", "author_fullname": "t2_elz04itb", "author_is_blocked": false, "author_patreon_flair": false, "author_premium": false, "awarders": [], "banned_at_utc": null, "banned_by": null, "body": "Maaf karna, galti me thoda idhar udhar hogaya", "can_gild": false, "can_mod_post": false, "collapsed": false, "collapsed_because_crowd_control": null, "collapsed_reason": null, "collapsed_reason_code": null, "comment_type": null, "controversiality": 0, "created": 1722506798, "created_utc": 1722506798, "distinguished": null, "downs": 0, "edited": false, "gilded": 0, "gildings": {}, "id": "lfybes5", "is_submitter": false, "likes": null, "link_id": "t3_1ehapj2", "locked": false, "mod_note": null, "mod_reason_by": null, "mod_reason_title": null, "mod_reports": [], "name": "t1_lfybes5", "no_follow": true, "num_reports": null, "parent_id": "t1_lfy5sqy", "permalink": "/r/Btechtards/comments/1ehapj2/tiering_of_colleges_does_not_make_any_sense/lfybes5/", "removal_reason": null, "replies": "", "report_reasons": null, "retrieved_on": 1722506814, "saved": false, "score": 3, "score_hidden": false, "send_replies": true, "stickied": false, "subreddit": "Btechtards", "subreddit_id": "t5_56z50y", "subreddit_name_prefixed": "r/Btechtards", "subreddit_type": "public", "top_awarded_type": null, "total_awards_received": 0, "treatment_tags": [], "unrepliable_reason": null, "ups": 3, "user_reports": []}, {"_meta": {"retrieved_2nd_on": 1722635086}, "all_awardings": [], "approved_at_utc": null, "approved_by": null, "archived": false, "associated_award": null, "author": "Temporary_Energy_712", "author_flair_background_color": null, "author_flair_css_class": null, "author_flair_richtext": [], "author_flair_template_id": null, "author_flair_text": null, "author_flair_text_color": null, "author_flair_type": "text", "author_fullname": "t2_10rcu564ay", "author_is_blocked": false, "author_patreon_flair": false, "author_premium": false, "awarders": [], "banned_at_utc": null, "banned_by": null, "body": "Hai hee tier 3", "can_gild": false, "can_mod_post": false, "collapsed": false, "collapsed_because_crowd_control": null, "collapsed_reason": null, "collapsed_reason_code": null, "comment_type": null, "controversiality": 0, "created": 1722505476, "created_utc": 1722505476, "distinguished": null, "downs": 0, "edited": false, "gilded": 0, "gildings": {}, "id": "lfy9dih", "is_submitter": false, "likes": null, "link_id": "t3_1ehapj2", "locked": false, "mod_note": null, "mod_reason_by": null, "mod_reason_title": null, "mod_reports": [], "name": "t1_lfy9dih", "no_follow": true, "num_reports": null, "parent_id": "t1_lfy5mm3", "permalink": "/r/Btechtards/comments/1ehapj2/tiering_of_colleges_does_not_make_any_sense/lfy9dih/", "removal_reason": null, "replies": "", "report_reasons": null, "retrieved_on": 1722505492, "saved": false, "score": 19, "score_hidden": false, "send_replies": true, "stickied": false, "subreddit": "Btechtards", "subreddit_id": "t5_56z50y", "subreddit_name_prefixed": "r/Btechtards", "subreddit_type": "public", "top_awarded_type": null, "total_awards_received": 0, "treatment_tags": [], "unrepliable_reason": null, "ups": 19, "user_reports": []}, {"_meta": {"retrieved_2nd_on": 1722635063}, "all_awardings": [], "approved_at_utc": null, "approved_by": null, "archived": false, "associated_award": null, "author": "Temporary_Energy_712", "author_flair_background_color": null, "author_flair_css_class": null, "author_flair_richtext": [], "author_flair_template_id": null, "author_flair_text": null, "author_flair_text_color": null, "author_flair_type": "text", "author_fullname": "t2_10rcu564ay", "author_is_blocked": false, "author_patreon_flair": false, "author_premium": false, "awarders": [], "banned_at_utc": null, "banned_by": null, "body": "Tier 2 - manipal main campus, thapar , top state government colleges like usict.", "can_gild": false, "can_mod_post": false, "collapsed": false, "collapsed_because_crowd_control": null, "collapsed_reason": null, "collapsed_reason_code": null, "comment_type": null, "controversiality": 1, "created": 1722505455, "created_utc": 1722505455, "distinguished": null, "downs": 0, "edited": false, "gilded": 0, "gildings": {}, "id": "lfy9cdz", "is_submitter": false, "likes": null, "link_id": "t3_1ehapj2", "locked": false, "mod_note": null, "mod_reason_by": null, "mod_reason_title": null, "mod_reports": [], "name": "t1_lfy9cdz", "no_follow": false, "num_reports": null, "parent_id": "t3_1ehapj2", "permalink": "/r/Btechtards/comments/1ehapj2/tiering_of_colleges_does_not_make_any_sense/lfy9cdz/", "removal_reason": null, "replies": "", "report_reasons": null, "retrieved_on": 1722505469, "saved": false, "score": -5, "score_hidden": false, "send_replies": true, "stickied": false, "subreddit": "Btechtards", "subreddit_id": "t5_56z50y", "subreddit_name_prefixed": "r/Btechtards", "subreddit_type": "public", "top_awarded_type": null, "total_awards_received": 0, "treatment_tags": [], "unrepliable_reason": null, "ups": -5, "user_reports": []}, {"_meta": {"retrieved_2nd_on": 1722634803}, "all_awardings": [], "approved_at_utc": null, "approved_by": null, "archived": false, "associated_award": null, "author": "Aggravating-Pie-2581", "author_flair_background_color": "#7193ff", "author_flair_css_class": null, "author_flair_richtext": [{"e": "text", "t": "NIT [ECE-VLSI]"}], "author_flair_template_id": "d9e093ee-2f3c-11ec-a123-a29163bdec27", "author_flair_text": "NIT [ECE-VLSI]", "author_flair_text_color": "light", "author_flair_type": "richtext", "author_fullname": "t2_ocvt3p1g", "author_is_blocked": false, "author_patreon_flair": false, "author_premium": false, "awarders": [], "banned_at_utc": null, "banned_by": null, "body": "VIT: Mujhe kyu toda?", "can_gild": false, "can_mod_post": false, "collapsed": false, "collapsed_because_crowd_control": null, "collapsed_reason": null, "collapsed_reason_code": null, "comment_type": null, "controversiality": 0, "created": 1722505194, "created_utc": 1722505194, "distinguished": null, "downs": 0, "edited": false, "gilded": 0, "gildings": {}, "id": "lfy8y5a", "is_submitter": false, "likes": null, "link_id": "t3_1ehapj2", "locked": false, "mod_note": null, "mod_reason_by": null, "mod_reason_title": null, "mod_reports": [], "name": "t1_lfy8y5a", "no_follow": true, "num_reports": null, "parent_id": "t1_lfy5mm3", "permalink": "/r/Btechtards/comments/1ehapj2/tiering_of_colleges_does_not_make_any_sense/lfy8y5a/", "removal_reason": null, "replies": "", "report_reasons": null, "retrieved_on": 1722505211, "saved": false, "score": 5, "score_hidden": false, "send_replies": true, "stickied": false, "subreddit": "Btechtards", "subreddit_id": "t5_56z50y", "subreddit_name_prefixed": "r/Btechtards", "subreddit_type": "public", "top_awarded_type": null, "total_awards_received": 0, "treatment_tags": [], "unrepliable_reason": null, "ups": 5, "user_reports": []}, {"_meta": {"retrieved_2nd_on": 1722634521}, "all_awardings": [], "approved_at_utc": null, "approved_by": null, "archived": false, "associated_award": null, "author": "Downtown_Outcome_992", "author_flair_background_color": "#0079d3", "author_flair_css_class": null, "author_flair_richtext": [{"e": "text", "t": "BTech"}], "author_flair_template_id": "7ee1ad6c-b616-11ee-a9bd-72a828abc383", "author_flair_text": "BTech", "author_flair_text_color": "light", "author_flair_type": "richtext", "author_fullname": "t2_8h91igppp", "author_is_blocked": false, "author_patreon_flair": false, "author_premium": false, "awarders": [], "banned_at_utc": null, "banned_by": null, "body": ">I think this is just a made up by students going to a college to satisfy their ego.\n\nNot really since most of the guys who mention this tier system are the ones who keep saying I am going tier 3 college or tier 69 college or whatever", "can_gild": false, "can_mod_post": false, "collapsed": false, "collapsed_because_crowd_control": null, "collapsed_reason": null, "collapsed_reason_code": null, "comment_type": null, "controversiality": 0, "created": 1722504909, "created_utc": 1722504909, "distinguished": null, "downs": 0, "edited": false, "gilded": 0, "gildings": {}, "id": "lfy8iul", "is_submitter": false, "likes": null, "link_id": "t3_1ehapj2", "locked": false, "mod_note": null, "mod_reason_by": null, "mod_reason_title": null, "mod_reports": [], "name": "t1_lfy8iul", "no_follow": true, "num_reports": null, "parent_id": "t3_1ehapj2", "permalink": "/r/Btechtards/comments/1ehapj2/tiering_of_colleges_does_not_make_any_sense/lfy8iul/", "removal_reason": null, "replies": "", "report_reasons": null, "retrieved_on": 1722504925, "saved": false, "score": 25, "score_hidden": false, "send_replies": true, "stickied": false, "subreddit": "Btechtards", "subreddit_id": "t5_56z50y", "subreddit_name_prefixed": "r/Btechtards", "subreddit_type": "public", "top_awarded_type": null, "total_awards_received": 0, "treatment_tags": [], "unrepliable_reason": null, "ups": 25, "user_reports": []}, {"_meta": {"retrieved_2nd_on": 1722633546}, "all_awardings": [], "approved_at_utc": null, "approved_by": null, "archived": false, "associated_award": null, "author": "L_uchiha_7", "author_flair_background_color": null, "author_flair_css_class": null, "author_flair_richtext": [], "author_flair_template_id": null, "author_flair_text": null, "author_flair_text_color": null, "author_flair_type": "text", "author_fullname": "t2_55b42ntq9", "author_is_blocked": false, "author_patreon_flair": false, "author_premium": false, "awarders": [], "banned_at_utc": null, "banned_by": null, "body": "Tier, is something created for ego satisfaction,\n\nI totally support that line\ud83d\ude24", "can_gild": false, "can_mod_post": false, "collapsed": false, "collapsed_because_crowd_control": null, "collapsed_reason": null, "collapsed_reason_code": null, "comment_type": null, "controversiality": 0, "created": 1722503937, "created_utc": 1722503937, "distinguished": null, "downs": 0, "edited": false, "gilded": 0, "gildings": {}, "id": "lfy745n", "is_submitter": false, "likes": null, "link_id": "t3_1ehapj2", "locked": false, "mod_note": null, "mod_reason_by": null, "mod_reason_title": null, "mod_reports": [], "name": "t1_lfy745n", "no_follow": true, "num_reports": null, "parent_id": "t3_1ehapj2", "permalink": "/r/Btechtards/comments/1ehapj2/tiering_of_colleges_does_not_make_any_sense/lfy745n/", "removal_reason": null, "replies": "", "report_reasons": null, "retrieved_on": 1722503951, "saved": false, "score": 59, "score_hidden": false, "send_replies": true, "stickied": false, "subreddit": "Btechtards", "subreddit_id": "t5_56z50y", "subreddit_name_prefixed": "r/Btechtards", "subreddit_type": "public", "top_awarded_type": null, "total_awards_received": 0, "treatment_tags": [], "unrepliable_reason": null, "ups": 59, "user_reports": []}, {"_meta": {"retrieved_2nd_on": 1722632640}, "all_awardings": [], "approved_at_utc": null, "approved_by": null, "archived": false, "associated_award": null, "author": "Athiktos-", "author_flair_background_color": "#cc5289", "author_flair_css_class": null, "author_flair_richtext": [{"e": "text", "t": " [CSE - Non Binary]"}], "author_flair_template_id": "910947cc-a17e-11ee-a0ae-e6bb5f57ae4f", "author_flair_text": " [CSE - Non Binary]", "author_flair_text_color": "light", "author_flair_type": "richtext", "author_fullname": "t2_10q7cbjs5c", "author_is_blocked": false, "author_patreon_flair": false, "author_premium": false, "awarders": [], "banned_at_utc": null, "banned_by": null, "body": "comma nahi lagega faltu mei kyu lagaya hai dumb lag rha hai", "can_gild": false, "can_mod_post": false, "collapsed": false, "collapsed_because_crowd_control": null, "collapsed_reason": null, "collapsed_reason_code": null, "comment_type": null, "controversiality": 0, "created": 1722503026, "created_utc": 1722503026, "distinguished": null, "downs": 0, "edited": false, "gilded": 0, "gildings": {}, "id": "lfy5sqy", "is_submitter": false, "likes": null, "link_id": "t3_1ehapj2", "locked": false, "mod_note": null, "mod_reason_by": null, "mod_reason_title": null, "mod_reports": [], "name": "t1_lfy5sqy", "no_follow": true, "num_reports": null, "parent_id": "t1_lfy39as", "permalink": "/r/Btechtards/comments/1ehapj2/tiering_of_colleges_does_not_make_any_sense/lfy5sqy/", "removal_reason": null, "replies": "", "report_reasons": null, "retrieved_on": 1722503044, "saved": false, "score": 41, "score_hidden": false, "send_replies": true, "stickied": false, "subreddit": "Btechtards", "subreddit_id": "t5_56z50y", "subreddit_name_prefixed": "r/Btechtards", "subreddit_type": "public", "top_awarded_type": null, "total_awards_received": 0, "treatment_tags": [], "unrepliable_reason": null, "ups": 41, "user_reports": []}, {"_meta": {"retrieved_2nd_on": 1722632513}, "all_awardings": [], "approved_at_utc": null, "approved_by": null, "archived": false, "associated_award": null, "author": "Leather_Ad2680", "author_flair_background_color": null, "author_flair_css_class": null, "author_flair_richtext": [], "author_flair_template_id": null, "author_flair_text": null, "author_flair_text_color": null, "author_flair_type": "text", "author_fullname": "t2_s7wt9i1u", "author_is_blocked": false, "author_patreon_flair": false, "author_premium": false, "awarders": [], "banned_at_utc": null, "banned_by": null, "body": "Jisko dekho VIT ko hi criticize karta hai", "can_gild": false, "can_mod_post": false, "collapsed": false, "collapsed_because_crowd_control": null, "collapsed_reason": null, "collapsed_reason_code": null, "comment_type": null, "controversiality": 0, "created": 1722502905, "created_utc": 1722502905, "distinguished": null, "downs": 0, "edited": false, "gilded": 0, "gildings": {}, "id": "lfy5mm3", "is_submitter": false, "likes": null, "link_id": "t3_1ehapj2", "locked": false, "mod_note": null, "mod_reason_by": null, "mod_reason_title": null, "mod_reports": [], "name": "t1_lfy5mm3", "no_follow": true, "num_reports": null, "parent_id": "t3_1ehapj2", "permalink": "/r/Btechtards/comments/1ehapj2/tiering_of_colleges_does_not_make_any_sense/lfy5mm3/", "removal_reason": null, "replies": "", "report_reasons": null, "retrieved_on": 1722502951, "saved": false, "score": 56, "score_hidden": false, "send_replies": true, "stickied": false, "subreddit": "Btechtards", "subreddit_id": "t5_56z50y", "subreddit_name_prefixed": "r/Btechtards", "subreddit_type": "public", "top_awarded_type": null, "total_awards_received": 0, "treatment_tags": [], "unrepliable_reason": null, "ups": 56, "user_reports": []}, {"_meta": {"retrieved_2nd_on": 1722630988}, "all_awardings": [], "approved_at_utc": null, "approved_by": null, "archived": false, "associated_award": null, "author": "creepykimchi", "author_flair_background_color": null, "author_flair_css_class": null, "author_flair_richtext": [], "author_flair_template_id": null, "author_flair_text": null, "author_flair_text_color": null, "author_flair_type": "text", "author_fullname": "t2_15kfa51dm3", "author_is_blocked": false, "author_patreon_flair": false, "author_premium": false, "awarders": [], "banned_at_utc": null, "banned_by": null, "body": "\ud83d\udc80", "can_gild": false, "can_mod_post": false, "collapsed": false, "collapsed_because_crowd_control": null, "collapsed_reason": null, "collapsed_reason_code": null, "comment_type": null, "controversiality": 0, "created": 1722501373, "created_utc": 1722501373, "distinguished": null, "downs": 0, "edited": false, "gilded": 0, "gildings": {}, "id": "lfy3ed0", "is_submitter": true, "likes": null, "link_id": "t3_1ehapj2", "locked": false, "mod_note": null, "mod_reason_by": null, "mod_reason_title": null, "mod_reports": [], "name": "t1_lfy3ed0", "no_follow": true, "num_reports": null, "parent_id": "t1_lfy39as", "permalink": "/r/Btechtards/comments/1ehapj2/tiering_of_colleges_does_not_make_any_sense/lfy3ed0/", "removal_reason": null, "replies": "", "report_reasons": null, "retrieved_on": 1722501385, "saved": false, "score": 5, "score_hidden": false, "send_replies": true, "stickied": false, "subreddit": "Btechtards", "subreddit_id": "t5_56z50y", "subreddit_name_prefixed": "r/Btechtards", "subreddit_type": "public", "top_awarded_type": null, "total_awards_received": 0, "treatment_tags": [], "unrepliable_reason": null, "ups": 5, "user_reports": []}, {"_meta": {"retrieved_2nd_on": 1722630888}, "all_awardings": [], "approved_at_utc": null, "approved_by": null, "archived": false, "associated_award": null, "author": "Super-Professor-3457", "author_flair_background_color": null, "author_flair_css_class": null, "author_flair_richtext": [], "author_flair_template_id": null, "author_flair_text": null, "author_flair_text_color": null, "author_flair_type": "text", "author_fullname": "t2_elz04itb", "author_is_blocked": false, "author_patreon_flair": false, "author_premium": false, "awarders": [], "banned_at_utc": null, "banned_by": null, "body": "Who hurt you by saying, that your college is tier3?\n(/s)", "can_gild": false, "can_mod_post": false, "collapsed": false, "collapsed_because_crowd_control": null, "collapsed_reason": null, "collapsed_reason_code": null, "comment_type": null, "controversiality": 0, "created": 1722501276, "created_utc": 1722501276, "distinguished": null, "downs": 0, "edited": false, "gilded": 0, "gildings": {}, "id": "lfy39as", "is_submitter": false, "likes": null, "link_id": "t3_1ehapj2", "locked": false, "mod_note": null, "mod_reason_by": null, "mod_reason_title": null, "mod_reports": [], "name": "t1_lfy39as", "no_follow": true, "num_reports": null, "parent_id": "t3_1ehapj2", "permalink": "/r/Btechtards/comments/1ehapj2/tiering_of_colleges_does_not_make_any_sense/lfy39as/", "removal_reason": null, "replies": "", "report_reasons": null, "retrieved_on": 1722501292, "saved": false, "score": 92, "score_hidden": false, "send_replies": true, "stickied": false, "subreddit": "Btechtards", "subreddit_id": "t5_56z50y", "subreddit_name_prefixed": "r/Btechtards", "subreddit_type": "public", "top_awarded_type": null, "total_awards_received": 0, "treatment_tags": [], "unrepliable_reason": null, "ups": 92, "user_reports": []}]