[{"all_awardings": [], "archived": false, "associated_award": null, "author": "Icy_Meringue_6078", "author_created_utc": 1608326108, "author_flair_background_color": null, "author_flair_css_class": null, "author_flair_richtext": [], "author_flair_template_id": null, "author_flair_text": null, "author_flair_text_color": null, "author_flair_type": "text", "author_fullname": "t2_9eaa500e", "author_patreon_flair": false, "author_premium": false, "body": "Specialization is for insects.", "can_gild": true, "collapsed": false, "collapsed_because_crowd_control": null, "collapsed_reason": null, "collapsed_reason_code": null, "comment_type": null, "controversiality": 0, "created_utc": 1662622238, "distinguished": null, "edited": false, "gilded": 0, "gildings": {}, "id": "ink7h9z", "is_submitter": false, "link_id": "t3_x89ajc", "locked": false, "name": "t1_ink7h9z", "no_follow": true, "parent_id": "t3_x89ajc", "permalink": "/r/Indian_Academia/comments/x89ajc/core_cse_or_cse_with_specialization_which_is/ink7h9z/", "retrieved_on": 1665088857, "score": -2, "score_hidden": false, "send_replies": true, "stickied": false, "subreddit": "Indian_Academia", "subreddit_id": "t5_idfco", "subreddit_name_prefixed": "r/Indian_Academia", "subreddit_type": "public", "top_awarded_type": null, "total_awards_received": 0, "treatment_tags": [], "unrepliable_reason": null, "ups": -2}, {"all_awardings": [], "archived": false, "associated_award": null, "author": "[deleted]", "author_created_utc": null, "author_flair_background_color": "", "author_flair_css_class": null, "author_flair_template_id": null, "author_flair_text": null, "author_flair_text_color": "dark", "body": "Cse with specialization.", "can_gild": false, "collapsed": true, "collapsed_because_crowd_control": null, "collapsed_reason": "comment score below threshold", "collapsed_reason_code": "LOW_SCORE", "comment_type": null, "controversiality": 0, "created_utc": 1662607114, "distinguished": null, "edited": false, "gilded": 0, "gildings": {}, "id": "injk1uf", "is_submitter": false, "link_id": "t3_x89ajc", "locked": false, "name": "t1_injk1uf", "no_follow": false, "parent_id": "t3_x89ajc", "permalink": "/r/Indian_Academia/comments/x89ajc/core_cse_or_cse_with_specialization_which_is/injk1uf/", "retrieved_on": 1665089667, "score": -5, "score_hidden": false, "send_replies": true, "stickied": false, "subreddit": "Indian_Academia", "subreddit_id": "t5_idfco", "subreddit_name_prefixed": "r/Indian_Academia", "subreddit_type": "public", "top_awarded_type": null, "total_awards_received": 0, "treatment_tags": [], "unrepliable_reason": null, "ups": -5}, {"all_awardings": [], "archived": false, "associated_award": null, "author": "bssgopi", "author_created_utc": 1516296933, "author_flair_background_color": null, "author_flair_css_class": null, "author_flair_richtext": [], "author_flair_template_id": null, "author_flair_text": null, "author_flair_text_color": null, "author_flair_type": "text", "author_fullname": "t2_sl2aifo", "author_patreon_flair": false, "author_premium": false, "body": "When you have the option, choose Core CSE. In any case, what they teach in college, doesn't help in your job directly. You will need to learn on the job. Rather, you must choose the core subjects that help you in learning on the job more effectively and efficiently.", "can_gild": true, "collapsed": false, "collapsed_because_crowd_control": null, "collapsed_reason": null, "collapsed_reason_code": null, "comment_type": null, "controversiality": 0, "created_utc": 1662604690, "distinguished": null, "edited": false, "gilded": 0, "gildings": {}, "id": "injf6ee", "is_submitter": false, "link_id": "t3_x89ajc", "locked": false, "name": "t1_injf6ee", "no_follow": false, "parent_id": "t3_x89ajc", "permalink": "/r/Indian_Academia/comments/x89ajc/core_cse_or_cse_with_specialization_which_is/injf6ee/", "retrieved_on": 1665089835, "score": 9, "score_hidden": false, "send_replies": true, "stickied": false, "subreddit": "Indian_Academia", "subreddit_id": "t5_idfco", "subreddit_name_prefixed": "r/Indian_Academia", "subreddit_type": "public", "top_awarded_type": null, "total_awards_received": 0, "treatment_tags": [], "unrepliable_reason": null, "ups": 9}, {"all_awardings": [], "archived": false, "associated_award": null, "author": "[deleted]", "author_created_utc": null, "author_flair_background_color": "", "author_flair_css_class": null, "author_flair_template_id": null, "author_flair_text": null, "author_flair_text_color": "dark", "body": "[removed]", "can_gild": true, "collapsed": true, "collapsed_because_crowd_control": null, "collapsed_reason": null, "collapsed_reason_code": "DELETED", "comment_type": null, "controversiality": 0, "created_utc": 1662567586, "distinguished": null, "edited": false, "gilded": 0, "gildings": {}, "id": "ingujhy", "is_submitter": false, "link_id": "t3_x89ajc", "locked": false, "name": "t1_ingujhy", "no_follow": true, "parent_id": "t1_ingu4f0", "permalink": "/r/Indian_Academia/comments/x89ajc/core_cse_or_cse_with_specialization_which_is/ingujhy/", "retrieved_on": 1665093072, "score": 1, "score_hidden": false, "send_replies": true, "stickied": false, "subreddit": "Indian_Academia", "subreddit_id": "t5_idfco", "subreddit_name_prefixed": "r/Indian_Academia", "subreddit_type": "public", "top_awarded_type": null, "total_awards_received": 0, "treatment_tags": [], "unrepliable_reason": null, "ups": 1}, {"all_awardings": [], "archived": false, "associated_award": null, "author": "[deleted]", "author_created_utc": null, "author_flair_background_color": "", "author_flair_css_class": null, "author_flair_template_id": null, "author_flair_text": null, "author_flair_text_color": "dark", "body": "[removed]", "can_gild": true, "collapsed": true, "collapsed_because_crowd_control": null, "collapsed_reason": null, "collapsed_reason_code": "DELETED", "comment_type": null, "controversiality": 0, "created_utc": 1662567428, "distinguished": null, "edited": false, "gilded": 0, "gildings": {}, "id": "ingu4f0", "is_submitter": false, "link_id": "t3_x89ajc", "locked": false, "name": "t1_ingu4f0", "no_follow": true, "parent_id": "t3_x89ajc", "permalink": "/r/Indian_Academia/comments/x89ajc/core_cse_or_cse_with_specialization_which_is/ingu4f0/", "retrieved_on": 1665093087, "score": 1, "score_hidden": false, "send_replies": false, "stickied": false, "subreddit": "Indian_Academia", "subreddit_id": "t5_idfco", "subreddit_name_prefixed": "r/Indian_Academia", "subreddit_type": "public", "top_awarded_type": null, "total_awards_received": 0, "treatment_tags": [], "unrepliable_reason": null, "ups": 1}]