[{"_meta": {"retrieved_2nd_on": 1720989490}, "all_awardings": [], "approved_at_utc": null, "approved_by": null, "archived": false, "associated_award": null, "author": "CaptainSJ11", "author_flair_background_color": null, "author_flair_css_class": null, "author_flair_richtext": [], "author_flair_template_id": null, "author_flair_text": null, "author_flair_text_color": null, "author_flair_type": "text", "author_fullname": "t2_bznydijf", "author_is_blocked": false, "author_patreon_flair": false, "author_premium": false, "awarders": [], "banned_at_utc": null, "banned_by": null, "body": "Bruh what a shit post", "can_gild": false, "can_mod_post": false, "collapsed": false, "collapsed_because_crowd_control": null, "collapsed_reason": null, "collapsed_reason_code": null, "comment_type": null, "controversiality": 0, "created": 1720859879, "created_utc": 1720859879, "distinguished": null, "downs": 0, "edited": false, "gilded": 0, "gildings": {}, "id": "lcyqh0h", "is_submitter": false, "likes": null, "link_id": "t3_xgmi0c", "locked": false, "mod_note": null, "mod_reason_by": null, "mod_reason_title": null, "mod_reports": [], "name": "t1_lcyqh0h", "no_follow": true, "num_reports": null, "parent_id": "t3_xgmi0c", "permalink": "/r/JEENEETards/comments/xgmi0c/ultimate_guide_for_those_who_need_help_in/lcyqh0h/", "removal_reason": null, "replies": "", "report_reasons": null, "retrieved_on": 1720859892, "saved": false, "score": 1, "score_hidden": false, "send_replies": true, "stickied": false, "subreddit": "JEENEETards", "subreddit_id": "t5_311ttu", "subreddit_name_prefixed": "r/JEENEETards", "subreddit_type": "public", "top_awarded_type": null, "total_awards_received": 0, "treatment_tags": [], "unrepliable_reason": null, "ups": 1, "user_reports": []}, {"_meta": {"removal_type": "deleted", "retrieved_2nd_on": 1719975641, "was_deleted_later": true}, "all_awardings": [], "approved_at_utc": null, "approved_by": null, "archived": false, "associated_award": null, "author": "Silly_Mongoose745", "author_flair_background_color": null, "author_flair_css_class": null, "author_flair_richtext": [], "author_flair_template_id": null, "author_flair_text": null, "author_flair_text_color": null, "author_flair_type": "text", "author_fullname": "t2_i2u99bcc", "author_is_blocked": false, "author_patreon_flair": false, "author_premium": false, "awarders": [], "banned_at_utc": null, "banned_by": null, "body": ",", "can_gild": false, "can_mod_post": false, "collapsed": false, "collapsed_because_crowd_control": null, "collapsed_reason": null, "collapsed_reason_code": null, "comment_type": null, "controversiality": 0, "created": 1719846029, "created_utc": 1719846029, "distinguished": null, "downs": 0, "edited": false, "gilded": 0, "gildings": {}, "id": "lb4vwc7", "is_submitter": false, "likes": null, "link_id": "t3_xgmi0c", "locked": false, "mod_note": null, "mod_reason_by": null, "mod_reason_title": null, "mod_reports": [], "name": "t1_lb4vwc7", "no_follow": true, "num_reports": null, "parent_id": "t1_iot1d9q", "permalink": "/r/JEENEETards/comments/xgmi0c/ultimate_guide_for_those_who_need_help_in/lb4vwc7/", "removal_reason": null, "replies": "", "report_reasons": null, "retrieved_on": 1719846046, "saved": false, "score": 1, "score_hidden": false, "send_replies": true, "stickied": false, "subreddit": "JEENEETards", "subreddit_id": "t5_311ttu", "subreddit_name_prefixed": "r/JEENEETards", "subreddit_type": "public", "top_awarded_type": null, "total_awards_received": 0, "treatment_tags": [], "unrepliable_reason": null, "ups": 1, "user_reports": []}, {"_meta": {"retrieved_2nd_on": 1719936143}, "all_awardings": [], "approved_at_utc": null, "approved_by": null, "archived": false, "associated_award": null, "author": "aintnoluvhere", "author_flair_background_color": null, "author_flair_css_class": null, "author_flair_richtext": [], "author_flair_template_id": null, "author_flair_text": null, "author_flair_text_color": null, "author_flair_type": "text", "author_fullname": "t2_jodrq35n", "author_is_blocked": false, "author_patreon_flair": false, "author_premium": false, "awarders": [], "banned_at_utc": null, "banned_by": null, "body": "+11", "can_gild": false, "can_mod_post": false, "collapsed": false, "collapsed_because_crowd_control": null, "collapsed_reason": null, "collapsed_reason_code": null, "comment_type": null, "controversiality": 0, "created": 1719806531, "created_utc": 1719806531, "distinguished": null, "downs": 0, "edited": false, "gilded": 0, "gildings": {}, "id": "lb2w01g", "is_submitter": false, "likes": null, "link_id": "t3_xgmi0c", "locked": false, "mod_note": null, "mod_reason_by": null, "mod_reason_title": null, "mod_reports": [], "name": "t1_lb2w01g", "no_follow": true, "num_reports": null, "parent_id": "t1_iot1d9q", "permalink": "/r/JEENEETards/comments/xgmi0c/ultimate_guide_for_those_who_need_help_in/lb2w01g/", "removal_reason": null, "replies": "", "report_reasons": null, "retrieved_on": 1719806548, "saved": false, "score": 1, "score_hidden": false, "send_replies": true, "stickied": false, "subreddit": "JEENEETards", "subreddit_id": "t5_311ttu", "subreddit_name_prefixed": "r/JEENEETards", "subreddit_type": "public", "top_awarded_type": null, "total_awards_received": 0, "treatment_tags": [], "unrepliable_reason": null, "ups": 1, "user_reports": []}, {"all_awardings": [], "archived": false, "associated_award": null, "author": "boogeyman6__9", "author_created_utc": 1656836382, "author_flair_background_color": null, "author_flair_css_class": null, "author_flair_richtext": [], "author_flair_template_id": null, "author_flair_text": null, "author_flair_text_color": null, "author_flair_type": "text", "author_fullname": "t2_pir2ai00", "author_patreon_flair": false, "author_premium": false, "body": "The nerve to put nsut(85%delhi quota) with nit Trichy.\nPlus bits Goa below that\ud83d\ude06\ud83e\udee3\n\nAnyways good work post is actually helpful.", "can_gild": true, "collapsed": false, "collapsed_because_crowd_control": null, "collapsed_reason": null, "collapsed_reason_code": null, "comment_type": null, "controversiality": 0, "created_utc": 1664404918, "distinguished": null, "edited": false, "gilded": 0, "gildings": {}, "id": "iqaods5", "is_submitter": false, "link_id": "t3_xgmi0c", "locked": false, "name": "t1_iqaods5", "no_follow": true, "parent_id": "t3_xgmi0c", "permalink": "/r/JEENEETards/comments/xgmi0c/ultimate_guide_for_those_who_need_help_in/iqaods5/", "retrieved_on": 1664971655, "score": 2, "score_hidden": false, "send_replies": true, "stickied": false, "subreddit": "JEENEETards", "subreddit_id": "t5_311ttu", "subreddit_name_prefixed": "r/JEENEETards", "subreddit_type": "public", "top_awarded_type": null, "total_awards_received": 0, "treatment_tags": [], "unrepliable_reason": null, "ups": 2}, {"all_awardings": [], "archived": false, "associated_award": null, "author": "[deleted]", "author_created_utc": null, "author_flair_background_color": "", "author_flair_css_class": null, "author_flair_template_id": null, "author_flair_text": null, "author_flair_text_color": "dark", "body": "[deleted]", "can_gild": true, "collapsed": true, "collapsed_because_crowd_control": null, "collapsed_reason": null, "collapsed_reason_code": "DELETED", "comment_type": null, "controversiality": 0, "created_utc": 1663439003, "distinguished": null, "edited": false, "gilded": 0, "gildings": {}, "id": "iotrgcc", "is_submitter": false, "link_id": "t3_xgmi0c", "locked": false, "name": "t1_iotrgcc", "no_follow": true, "parent_id": "t1_iosqmmr", "permalink": "/r/JEENEETards/comments/xgmi0c/ultimate_guide_for_those_who_need_help_in/iotrgcc/", "retrieved_on": 1665033525, "score": 1, "score_hidden": false, "send_replies": true, "stickied": false, "subreddit": "JEENEETards", "subreddit_id": "t5_311ttu", "subreddit_name_prefixed": "r/JEENEETards", "subreddit_type": "public", "top_awarded_type": null, "total_awards_received": 0, "treatment_tags": [], "unrepliable_reason": null, "ups": 1}, {"all_awardings": [], "archived": false, "associated_award": null, "author": "[deleted]", "author_created_utc": null, "author_flair_background_color": "", "author_flair_css_class": null, "author_flair_template_id": null, "author_flair_text": null, "author_flair_text_color": "dark", "body": "lmao mai to bc isko award dene wala tha , accha hua tune bata diya", "can_gild": false, "collapsed": false, "collapsed_because_crowd_control": null, "collapsed_reason": null, "collapsed_reason_code": null, "comment_type": null, "controversiality": 0, "created_utc": 1663434788, "distinguished": null, "edited": false, "gilded": 0, "gildings": {}, "id": "ioth6qa", "is_submitter": false, "link_id": "t3_xgmi0c", "locked": false, "name": "t1_ioth6qa", "no_follow": false, "parent_id": "t1_iosqmmr", "permalink": "/r/JEENEETards/comments/xgmi0c/ultimate_guide_for_those_who_need_help_in/ioth6qa/", "retrieved_on": 1665033862, "score": 1, "score_hidden": false, "send_replies": true, "stickied": false, "subreddit": "JEENEETards", "subreddit_id": "t5_311ttu", "subreddit_name_prefixed": "r/JEENEETards", "subreddit_type": "public", "top_awarded_type": null, "total_awards_received": 0, "treatment_tags": [], "unrepliable_reason": null, "ups": 1}, {"all_awardings": [], "archived": false, "associated_award": null, "author": "HeftyGazelle8092", "author_created_utc": 1614126921, "author_flair_background_color": null, "author_flair_css_class": null, "author_flair_richtext": [], "author_flair_template_id": null, "author_flair_text": null, "author_flair_text_color": null, "author_flair_type": "text", "author_fullname": "t2_ajg7wupa", "author_patreon_flair": false, "author_premium": false, "body": "Outdated list", "can_gild": true, "collapsed": false, "collapsed_because_crowd_control": null, "collapsed_reason": null, "collapsed_reason_code": null, "comment_type": null, "controversiality": 0, "created_utc": 1663428525, "distinguished": null, "edited": false, "gilded": 0, "gildings": {}, "id": "iot1yvl", "is_submitter": false, "link_id": "t3_xgmi0c", "locked": false, "name": "t1_iot1yvl", "no_follow": false, "parent_id": "t3_xgmi0c", "permalink": "/r/JEENEETards/comments/xgmi0c/ultimate_guide_for_those_who_need_help_in/iot1yvl/", "retrieved_on": 1665034367, "score": 5, "score_hidden": false, "send_replies": true, "stickied": false, "subreddit": "JEENEETards", "subreddit_id": "t5_311ttu", "subreddit_name_prefixed": "r/JEENEETards", "subreddit_type": "public", "top_awarded_type": null, "total_awards_received": 0, "treatment_tags": [], "unrepliable_reason": null, "ups": 5}, {"all_awardings": [], "archived": false, "associated_award": null, "author": "yeetusboi97", "author_created_utc": 1599547046, "author_flair_background_color": "#73ad34", "author_flair_css_class": null, "author_flair_richtext": [{"a": ":kekw:", "e": "emoji", "u": "https://emoji.redditmedia.com/b66n76ietax81_t5_311ttu/kekw"}, {"e": "text", "t": "KAMEDDI"}, {"a": ":kekw:", "e": "emoji", "u": "https://emoji.redditmedia.com/b66n76ietax81_t5_311ttu/kekw"}], "author_flair_template_id": "a3400e9a-cb0a-11ec-a796-26ff444f3fa0", "author_flair_text": ":kekw:KAMEDDI:kekw:", "author_flair_text_color": "dark", "author_flair_type": "richtext", "author_fullname": "t2_804p8ky5", "author_patreon_flair": false, "author_premium": false, "body": "Haven't seen a shittier tier list before before. And DTU CS over IIT B ECE lmao ?", "can_gild": true, "collapsed": false, "collapsed_because_crowd_control": null, "collapsed_reason": null, "collapsed_reason_code": null, "comment_type": null, "controversiality": 0, "created_utc": 1663428279, "distinguished": null, "edited": false, "gilded": 0, "gildings": {}, "id": "iot1d9q", "is_submitter": false, "link_id": "t3_xgmi0c", "locked": false, "name": "t1_iot1d9q", "no_follow": false, "parent_id": "t3_xgmi0c", "permalink": "/r/JEENEETards/comments/xgmi0c/ultimate_guide_for_those_who_need_help_in/iot1d9q/", "retrieved_on": 1665034387, "score": 18, "score_hidden": false, "send_replies": true, "stickied": false, "subreddit": "JEENEETards", "subreddit_id": "t5_311ttu", "subreddit_name_prefixed": "r/JEENEETards", "subreddit_type": "public", "top_awarded_type": null, "total_awards_received": 0, "treatment_tags": [], "unrepliable_reason": null, "ups": 18}, {"all_awardings": [], "archived": false, "associated_award": null, "author": "yeetusboi97", "author_created_utc": 1599547046, "author_flair_background_color": "#73ad34", "author_flair_css_class": null, "author_flair_richtext": [{"a": ":kekw:", "e": "emoji", "u": "https://emoji.redditmedia.com/b66n76ietax81_t5_311ttu/kekw"}, {"e": "text", "t": "KAMEDDI"}, {"a": ":kekw:", "e": "emoji", "u": "https://emoji.redditmedia.com/b66n76ietax81_t5_311ttu/kekw"}], "author_flair_template_id": "a3400e9a-cb0a-11ec-a796-26ff444f3fa0", "author_flair_text": ":kekw:KAMEDDI:kekw:", "author_flair_text_color": "dark", "author_flair_type": "richtext", "author_fullname": "t2_804p8ky5", "author_patreon_flair": false, "author_premium": false, "body": "He lost me there", "can_gild": true, "collapsed": false, "collapsed_because_crowd_control": null, "collapsed_reason": null, "collapsed_reason_code": null, "comment_type": null, "controversiality": 0, "created_utc": 1663428129, "distinguished": null, "edited": false, "gilded": 0, "gildings": {}, "id": "iot10hl", "is_submitter": false, "link_id": "t3_xgmi0c", "locked": false, "name": "t1_iot10hl", "no_follow": false, "parent_id": "t1_iosogi6", "permalink": "/r/JEENEETards/comments/xgmi0c/ultimate_guide_for_those_who_need_help_in/iot10hl/", "retrieved_on": 1665034399, "score": 14, "score_hidden": false, "send_replies": true, "stickied": false, "subreddit": "JEENEETards", "subreddit_id": "t5_311ttu", "subreddit_name_prefixed": "r/JEENEETards", "subreddit_type": "public", "top_awarded_type": null, "total_awards_received": 0, "treatment_tags": [], "unrepliable_reason": null, "ups": 14}, {"all_awardings": [], "archived": false, "associated_award": null, "author": "Just_Monika5772", "author_created_utc": 1607695594, "author_flair_background_color": "#ddbd37", "author_flair_css_class": null, "author_flair_richtext": [{"e": "text", "t": "JEEtard"}], "author_flair_template_id": "9bd11a3a-e91d-11ea-82d5-0ea78b3c3e39", "author_flair_text": "JEEtard", "author_flair_text_color": "dark", "author_flair_type": "richtext", "author_fullname": "t2_99yjpp1o", "author_patreon_flair": false, "author_premium": false, "body": "\ud83d\udc80", "can_gild": true, "collapsed": false, "collapsed_because_crowd_control": null, "collapsed_reason": null, "collapsed_reason_code": null, "comment_type": null, "controversiality": 0, "created_utc": 1663427915, "distinguished": null, "edited": false, "gilded": 0, "gildings": {}, "id": "iot0i1l", "is_submitter": false, "link_id": "t3_xgmi0c", "locked": false, "name": "t1_iot0i1l", "no_follow": false, "parent_id": "t1_iosogi6", "permalink": "/r/JEENEETards/comments/xgmi0c/ultimate_guide_for_those_who_need_help_in/iot0i1l/", "retrieved_on": 1665034416, "score": 5, "score_hidden": false, "send_replies": true, "stickied": false, "subreddit": "JEENEETards", "subreddit_id": "t5_311ttu", "subreddit_name_prefixed": "r/JEENEETards", "subreddit_type": "public", "top_awarded_type": null, "total_awards_received": 0, "treatment_tags": [], "unrepliable_reason": null, "ups": 5}, {"all_awardings": [], "archived": false, "associated_award": null, "author": "Powerful-Implement29", "author_created_utc": 1660893576, "author_flair_background_color": null, "author_flair_css_class": null, "author_flair_richtext": [], "author_flair_template_id": null, "author_flair_text": null, "author_flair_text_color": null, "author_flair_type": "text", "author_fullname": "t2_ro6v40mh", "author_patreon_flair": false, "author_premium": false, "body": "tera wait kar raha tha bc", "can_gild": true, "collapsed": false, "collapsed_because_crowd_control": null, "collapsed_reason": null, "collapsed_reason_code": null, "comment_type": null, "controversiality": 0, "created_utc": 1663424832, "distinguished": null, "edited": false, "gilded": 0, "gildings": {}, "id": "ioste88", "is_submitter": true, "link_id": "t3_xgmi0c", "locked": false, "name": "t1_ioste88", "no_follow": false, "parent_id": "t1_iosqmmr", "permalink": "/r/JEENEETards/comments/xgmi0c/ultimate_guide_for_those_who_need_help_in/ioste88/", "retrieved_on": 1665034652, "score": 8, "score_hidden": false, "send_replies": true, "stickied": false, "subreddit": "JEENEETards", "subreddit_id": "t5_311ttu", "subreddit_name_prefixed": "r/JEENEETards", "subreddit_type": "public", "top_awarded_type": null, "total_awards_received": 0, "treatment_tags": [], "unrepliable_reason": null, "ups": 8}, {"all_awardings": [], "archived": false, "associated_award": null, "author": "Material_Focus8688", "author_created_utc": null, "author_flair_background_color": null, "author_flair_css_class": null, "author_flair_richtext": [], "author_flair_template_id": null, "author_flair_text": null, "author_flair_text_color": null, "author_flair_type": "text", "author_fullname": "t2_ry3n27ld", "author_patreon_flair": false, "author_premium": false, "body": "[credits toh de deta haraami insaan](https://workat.tech/general/article/choosing-engineering-college-branch-ageyubs2sxip)", "can_gild": true, "collapsed": false, "collapsed_because_crowd_control": null, "collapsed_reason": null, "collapsed_reason_code": null, "comment_type": null, "controversiality": 0, "created_utc": 1663423575, "distinguished": null, "edited": false, "gilded": 0, "gildings": {}, "id": "iosqmmr", "is_submitter": false, "link_id": "t3_xgmi0c", "locked": false, "name": "t1_iosqmmr", "no_follow": false, "parent_id": "t3_xgmi0c", "permalink": "/r/JEENEETards/comments/xgmi0c/ultimate_guide_for_those_who_need_help_in/iosqmmr/", "retrieved_on": 1665034743, "score": 14, "score_hidden": false, "send_replies": true, "stickied": false, "subreddit": "JEENEETards", "subreddit_id": "t5_311ttu", "subreddit_name_prefixed": "r/JEENEETards", "subreddit_type": "public", "top_awarded_type": null, "total_awards_received": 0, "treatment_tags": [], "unrepliable_reason": null, "ups": 14}, {"all_awardings": [], "archived": false, "associated_award": null, "author": "BanditSwimmer", "author_created_utc": 1652973422, "author_flair_background_color": null, "author_flair_css_class": null, "author_flair_richtext": [], "author_flair_template_id": null, "author_flair_text": null, "author_flair_text_color": null, "author_flair_type": "text", "author_fullname": "t2_ilxkq9dp", "author_patreon_flair": false, "author_premium": false, "body": "eh what crap? I didn\u2019t even know there were tier 1.1, 1.2, 1.3 subdivisions", "can_gild": true, "collapsed": false, "collapsed_because_crowd_control": null, "collapsed_reason": null, "collapsed_reason_code": null, "comment_type": null, "controversiality": 0, "created_utc": 1663423567, "distinguished": null, "edited": false, "gilded": 0, "gildings": {}, "id": "iosqm01", "is_submitter": false, "link_id": "t3_xgmi0c", "locked": false, "name": "t1_iosqm01", "no_follow": false, "parent_id": "t3_xgmi0c", "permalink": "/r/JEENEETards/comments/xgmi0c/ultimate_guide_for_those_who_need_help_in/iosqm01/", "retrieved_on": 1665034744, "score": 6, "score_hidden": false, "send_replies": true, "stickied": false, "subreddit": "JEENEETards", "subreddit_id": "t5_311ttu", "subreddit_name_prefixed": "r/JEENEETards", "subreddit_type": "public", "top_awarded_type": null, "total_awards_received": 0, "treatment_tags": [], "unrepliable_reason": null, "ups": 6}, {"all_awardings": [], "archived": false, "associated_award": null, "author": "[deleted]", "author_created_utc": null, "author_flair_background_color": "", "author_flair_css_class": null, "author_flair_template_id": null, "author_flair_text": null, "author_flair_text_color": "dark", "body": "[deleted]", "can_gild": true, "collapsed": true, "collapsed_because_crowd_control": null, "collapsed_reason": null, "collapsed_reason_code": "DELETED", "comment_type": null, "controversiality": 0, "created_utc": 1663422564, "distinguished": null, "edited": 1663422806, "gilded": 0, "gildings": {}, "id": "iosogi6", "is_submitter": false, "link_id": "t3_xgmi0c", "locked": false, "name": "t1_iosogi6", "no_follow": false, "parent_id": "t3_xgmi0c", "permalink": "/r/JEENEETards/comments/xgmi0c/ultimate_guide_for_those_who_need_help_in/iosogi6/", "retrieved_on": 1665034815, "score": 22, "score_hidden": false, "send_replies": true, "stickied": false, "subreddit": "JEENEETards", "subreddit_id": "t5_311ttu", "subreddit_name_prefixed": "r/JEENEETards", "subreddit_type": "public", "top_awarded_type": null, "total_awards_received": 0, "treatment_tags": [], "unrepliable_reason": null, "ups": 22}]